Workbook

Sheet INFO
B2: Ticker | E2: AAPL | I2: Description
B3: Name | E3: {=_xldudf_WISEPRICE($E$2,B3)} -> Apple Inc. | I3: {=_xldudf_WISEPRICE(E2,I2)} -> Apple Inc. is a global technology corporation that specializes in the conceptualization, production, and sale of a diverse suite of electronic devices. Its comprehensive hardware lineup features the well-known iPhone smartphones, Mac personal computers, and versatile iPad tablets. The company also supplies a range of wearables, smart home products, and accessories, including AirPods, Apple TV, Apple Watch, items from the Beats brand, and HomePod speakers. Beyond its device offerings, Apple delivers essential support services like AppleCare and robust cloud solutions. It oversees key digital platforms, prominently the App Store, which acts as a central hub for customers to discover and download countless applications and digital content, from e-books and music to videos, games, and podcasts. The company also generates revenue via advertising, leveraging both its proprietary ad platforms and third-party licensing deals. Apple's ecosystem is further bolstered by a wide array of subscription-based services: Apple Arcade for gaming, Apple Fitness+ for personalized wellness, Apple Music for curated audio experiences and on-demand radio, Apple News+ for access to news and magazines, and Apple TV+ for exclusive original video programming. Its financial services portfolio includes the co-branded Apple Card and the mobile payment system, Apple Pay. Additionally, Apple strategically licenses its intellectual property. The company serves a broad clientele that spans individual consumers, small and medium-sized enterprises, as well as institutional clients in the education, corporate, and governmental sectors. Products are distributed through a multi-channel strategy, utilizing Apple's own physical retail locations and online storefronts, a dedicated direct sales team, and collaborations with external partners such as mobile network providers, wholesalers, general retailers, and authorized resellers. The App Store additionally functions as the primary conduit for third-party applications designed for its devices. Founded in 1976, Apple Inc. is headquartered in Cupertino, California.
B4: Market cap | E4: {=_xldudf_WISE(E2,B4,Y13)/1000000} -> 4810109.1 | F4: 2577253
B5: Sector | E5: {=_xldudf_WISEPRICE($E$2,B5:B10)} -> Technology
B6: Industry | E6: Consumer Electronics
B7: Exchange Short Name | E7: NASDAQ
B8: IPODate | E8: 1980-12-12
B9: Full Time Employees | E9: 166000
B10: Website | E10: https://www.apple.com
B11: Analysis Year | E11: 2023
B13: Year | G13: =H13-1 -> 2006 | H13: =I13-1 -> 2007 | I13: =J13-1 -> 2008 | J13: =K13-1 -> 2009 | K13: =L13-1 -> 2010 | L13: =M13-1 -> 2011 | M13: =N13-1 -> 2012 | N13: =O13-1 -> 2013 | ... W13: =X13-1 -> 2022 | X13: =E11 -> 2023 | Y13: TTM | AA13: Z-score (Default Risk)
B14: Revenue | G14: {=_xldudf_WISE($E$2,$B14:$B15,G$13:Y$13)/1000000} -> 19315 | H14: 24006 | I14: 32479 | J14: 42603 | K14: 65225 | L14: 108249 | M14: 156508 | N14: 170910 | O14: 182795 | P14: 233715 | Q14: 215639 | R14: 229234 | S14: 265595 | T14: 260174 | U14: 274515 | V14: 365817 | W14: 394328 | X14: 383285 | Y14: 451442 | AD14: =E11 -> 2023 | AE14: TTM
B15: Gross Profit | G15: 5598 | H15: 8154 | I15: 11145 | J15: 16852 | K15: 25684 | L15: 43818 | M15: 68662 | N15: 64304 | O15: 70537 | P15: 93626 | Q15: 84263 | R15: 88186 | S15: 101839 | T15: 98392 | U15: 104956 | V15: 152836 | W15: 170782 | X15: 169148 | Y15: 216071 | AA15: Current Assets | AD15: {=_xldudf_WISE($E$2,"Total current assets",AD$14:AE$14)/1000000} -> 143566 | AE15: 144114
B16: Gross Margin | G16: =IFERROR((G15/G14),"") -> 0.28982656 | H16: =IFERROR((H15/H14),"") -> 0.33966508 | I16: =IFERROR((I15/I14),"") -> 0.3431448 | J16: =IFERROR((J15/J14),"") -> 0.395559 | K16: =IFERROR((K15/K14),"") -> 0.39377539 | L16: =IFERROR((L15/L14),"") -> 0.40478896 | M16: =IFERROR((M15/M14),"") -> 0.4387124 | N16: =IFERROR((N15/N14),"") -> 0.37624481 | ... Y16: =IFERROR((Y15/Y14),"") -> 0.47862405 | AA16: Current Liabilities | AD16: {=_xldudf_WISE($E$2,"Total current liabilities",AD$14:AE$14)/1000000} -> 145308 | AE16: 134641
B17: EBITDA | G17: {=_xldudf_WISE($E$2,$B17:$B18,G$13:Y$13)/1000000} -> 2678 | H17: 4724 | I17: 7304 | J17: 12029 | K17: 19412 | L17: 36019 | M17: 59040 | N17: 57048 | O17: 61813 | P17: 84505 | Q17: 73333 | R17: 76569 | S17: 87046 | T17: 81860 | U17: 81020 | V17: 123136 | W17: 133138 | X17: 129188 | Y17: 160332 | AA17: Net Working Capital | AD17: {=_xldudf_WISE($E$2,"Working capital",AD$14:AE$14)/1000000} -> -1742 | AE17: 9473
B18: Net Income | G18: 1989 | H18: 3495 | I18: 4834 | J18: 8235 | K18: 14013 | L18: 25922 | M18: 41733 | N18: 37037 | O18: 39510 | P18: 53394 | Q18: 45687 | R18: 48351 | S18: 59531 | T18: 55256 | U18: 57411 | V18: 94680 | W18: 99803 | X18: 96995 | Y18: 122575 | AA18: Total Assets | AD18: {=_xldudf_WISE($E$2,$AA18:$AA20,AD$14:AE$14)/1000000} -> 352583 | AE18: 371082
B19: Net Margin | G19: =IFERROR((G18/G14),"") -> 0.10297696 | H19: =IFERROR((H18/H14),"") -> 0.1455886 | I19: =IFERROR((I18/I14),"") -> 0.14883463 | J19: =IFERROR((J18/J14),"") -> 0.19329625 | K19: =IFERROR((K18/K14),"") -> 0.21484094 | L19: =IFERROR((L18/L14),"") -> 0.23946642 | M19: =IFERROR((M18/M14),"") -> 0.26665091 | N19: =IFERROR((N18/N14),"") -> 0.2167047 | ... Y19: =IFERROR((Y18/Y14),"") -> 0.27151882 | AA19: Retained Earnings | AD19: -214 | AE19: 12359
B20: EPS | G20: {=_xldudf_WISE(E2,B20,G13:Y13)} -> 0.08 | H20: 0.14 | I20: 0.2 | J20: 0.33 | K20: 0.55 | L20: 1 | M20: 1.59 | N20: 1.43 | O20: 1.62 | P20: 2.32 | Q20: 2.09 | R20: 2.32 | S20: 3 | T20: 2.99 | U20: 3.31 | V20: 5.67 | W20: 6.15 | X20: 6.16 | Y20: 8.29 | AA20: Operating Income | AD20: 114301 | AE20: 147366
B21: Free Cash Flow | G21: {=_xldudf_WISE($E$2,$B21,G$13:Y$13)/1000000} -> 1563 | H21: 4484 | I21: 8397 | J21: 8946 | K21: 16474 | L21: 30077 | M21: 41454 | N21: 44590 | O21: 49900 | P21: 69778 | Q21: 52683 | R21: 51430 | S21: 64121 | T21: 58896 | U21: 73365 | V21: 92953 | W21: 111443 | X21: 99584 | Y21: 129174 | AA21: Basic Shares Outstanding | AD21: {=_xldudf_WISE($E$2,"Weighted Average Shs Out",AD$14:AE$14)/1000000} -> 15744.231 | AE21: 14710.718
B22: Rev % | H22: =IFERROR((H14-G14)/G14,"") -> 0.24286824 | I22: =IFERROR((I14-H14)/H14,"") -> 0.35295343 | J22: =IFERROR((J14-I14)/I14,"") -> 0.3117091 | K22: =IFERROR((K14-J14)/J14,"") -> 0.53099547 | L22: =IFERROR((L14-K14)/K14,"") -> 0.65962438 | M22: =IFERROR((M14-L14)/L14,"") -> 0.44581474 | N22: =IFERROR((N14-M14)/M14,"") -> 0.092020855 | O22: =IFERROR((O14-N14)/N14,"") -> 0.069539524 | ... X22: =IFERROR((X14-W14)/W14,"") -> -0.028004605 | AA22: Stock Price | AD22: {=_xldudf_WISEPRICE($E$2,"price")} -> 327.5 | AE22: {=_xldudf_WISEPRICE($E$2,"price")} -> 327.5
B23: Gross Profit % | H23: =IFERROR((H15-G15)/G15,"") -> 0.45659164 | I23: =IFERROR((I15-H15)/H15,"") -> 0.36681383 | J23: =IFERROR((J15-I15)/I15,"") -> 0.51206819 | K23: =IFERROR((K15-J15)/J15,"") -> 0.5240921 | L23: =IFERROR((L15-K15)/K15,"") -> 0.70604267 | M23: =IFERROR((M15-L15)/L15,"") -> 0.56698161 | N23: =IFERROR((N15-M15)/M15,"") -> -0.063470333 | O23: =IFERROR((O15-N15)/N15,"") -> 0.096930207 | ... X23: =IFERROR((X15-W15)/W15,"") -> -0.009567753 | AA23: Market Cap | AD23: {=_xldudf_WISE($E$2,$AA23:$AA25,AD$14:AE$14)/1000000} -> 2695569.8 | AE23: 4810109.1
B24: Net Income % | H24: =IFERROR((H18-G18)/G18,"") -> 0.7571644 | I24: =IFERROR((I18-H18)/H18,"") -> 0.38311874 | J24: =IFERROR((J18-I18)/I18,"") -> 0.70355813 | K24: =IFERROR((K18-J18)/J18,"") -> 0.70163934 | L24: =IFERROR((L18-K18)/K18,"") -> 0.84985371 | M24: =IFERROR((M18-L18)/L18,"") -> 0.60994522 | N24: =IFERROR((N18-M18)/M18,"") -> -0.11252486 | O24: =IFERROR((O18-N18)/N18,"") -> 0.066771067 | ... X24: =IFERROR((X18-W18)/W18,"") -> -0.028135427 | AA24: Total Liabilities | AD24: 290437 | AE24: 264591
B25: EPS % | H25: =IFERROR((H20-G20)/G20,"") -> 0.75 | I25: =IFERROR((I20-H20)/H20,"") -> 0.42857143 | J25: =IFERROR((J20-I20)/I20,"") -> 0.65 | K25: =IFERROR((K20-J20)/J20,"") -> 0.66666667 | L25: =IFERROR((L20-K20)/K20,"") -> 0.81818182 | M25: =IFERROR((M20-L20)/L20,"") -> 0.59 | N25: =IFERROR((N20-M20)/M20,"") -> -0.10062893 | O25: =IFERROR((O20-N20)/N20,"") -> 0.13286713 | ... X25: =IFERROR((X20-W20)/W20,"") -> 0.0016260163 | AA25: Revenue | AD25: 383285 | AE25: 451442
B26: Free Cash Flow % | H26: =IFERROR((H21-G21)/G21,"") -> 1.868842 | I26: =IFERROR((I21-H21)/H21,"") -> 0.87265834 | J26: =IFERROR((J21-I21)/I21,"") -> 0.065380493 | K26: =IFERROR((K21-J21)/J21,"") -> 0.8414934 | L26: =IFERROR((L21-K21)/K21,"") -> 0.82572539 | M26: =IFERROR((M21-L21)/L21,"") -> 0.37826246 | N26: =IFERROR((N21-M21)/M21,"") -> 0.075650118 | O26: =IFERROR((O21-N21)/N21,"") -> 0.119085 | ... X26: =IFERROR((X21-W21)/W21,"") -> -0.10641314
B27: Cash And Cash Equivalents | G27: {=_xldudf_WISE($E$2,$B27:$B30,G$13:Y$13)/1000000} -> 6392 | H27: 9352 | I27: 11875 | J27: 5263 | K27: 11261 | L27: 9815 | M27: 10746 | N27: 14259 | O27: 13844 | P27: 21120 | Q27: 20484 | R27: 20289 | S27: 25913 | T27: 48844 | U27: 38016 | V27: 34940 | W27: 23646 | X27: 29965 | Y27: 36328 | AA27: Coefficient | AD27: Variables
B28: Selling General And Administrative Expenses | G28: 2433 | H28: 2963 | I28: 3761 | J28: 4149 | K28: 5517 | L28: 7599 | M28: 10040 | N28: 10830 | O28: 11993 | P28: 14329 | Q28: 14194 | R28: 15261 | S28: 16705 | T28: 18245 | U28: 19916 | V28: 21973 | W28: 25094 | X28: 24932 | Y28: 28667 | AA28: 1.2 | AD28: =(AD15-AD16)/AD18 -> -0.0049406806 | AE28: =(AE15-AE16)/AE18 -> 0.02552805
B29: Short Term Debt | G29: 0 | H29: 0 | I29: 0 | J29: 0 | K29: 0 | L29: 0 | M29: 0 | N29: 0 | O29: 6308 | P29: 10999 | Q29: 11605 | R29: 18473 | S29: 20748 | T29: 16240 | U29: 15229 | V29: 17141 | W29: 22773 | X29: 17382 | Y29: 10307 | AA29: 1.4 | AD29: =AD19/AD18 -> -0.00060694929 | AE29: =AE19/AE18 -> 0.033305307
B30: Research And Development Expenses | G30: 712 | H30: 782 | I30: 1109 | J30: 1333 | K30: 1782 | L30: 2429 | M30: 3381 | N30: 4475 | O30: 6041 | P30: 8067 | Q30: 10045 | R30: 11581 | S30: 14236 | T30: 16217 | U30: 18752 | V30: 21914 | W30: 26251 | X30: 29915 | Y30: 40038 | AA30: 3.3 | AD30: =AD20/AD18 -> 0.32418182 | AE30: =AE20/AE18 -> 0.39712516
B31: Revenue Per Share | G31: =IFERROR(G14/G45,"") -> 0.78609799 | H31: =IFERROR(H14/H45,"") -> 0.96408957 | I31: =IFERROR(I14/I45,"") -> 1.2857933 | J31: =IFERROR(J14/J45,"") -> 1.6775367 | K31: =IFERROR(K14/K45,"") -> 2.5191216 | L31: =IFERROR(L14/L45,"") -> 4.1275357 | M31: =IFERROR(M14/M45,"") -> 5.912671 | N31: =IFERROR(N14/N45,"") -> 6.5516556 | ... Y31: =IFERROR(Y14/Y45,"") -> 30.568695 | AA31: 0.6 | AD31: =AD23/AD24 -> 9.2810826 | AE31: =AE23/AE24 -> 18.179413
B32: Net Income Per Share | G32: =IFERROR(G18/G45,"") -> 0.080949982 | H32: =IFERROR(H18/H45,"") -> 0.14036045 | I32: =IFERROR(I18/I45,"") -> 0.19137057 | J32: =IFERROR(J18/J45,"") -> 0.32426155 | K32: =IFERROR(K18/K45,"") -> 0.54121044 | L32: =IFERROR(L18/L45,"") -> 0.98840619 | M32: =IFERROR(M18/M45,"") -> 1.5766191 | N32: =IFERROR(N18/N45,"") -> 1.4197746 | ... Y32: =IFERROR(Y18/Y45,"") -> 8.299976 | AA32: 1 | AD32: =AD25/AD18 -> 1.0870774 | AE32: =AE25/AE18 -> 1.2165559
B33: Free Cash Flow Per Share | G33: =IFERROR(G21/G45,"") -> 0.063612279 | H33: =IFERROR(H21/H45,"") -> 0.18007905 | I33: =IFERROR(I21/I45,"") -> 0.33242422 | J33: =IFERROR(J21/J45,"") -> 0.3522579 | K33: =IFERROR(K21/K45,"") -> 0.63625924 | L33: =IFERROR(L21/L45,"") -> 1.1468364 | M33: =IFERROR(M21/M45,"") -> 1.5660788 | N33: =IFERROR(N21/N45,"") -> 1.7093109 | ... Y33: =IFERROR(Y21/Y45,"") -> 8.746817 | AD33: =SUMPRODUCT(AA28:AA32,AD28:AD32) -> 7.7187484 | AE33: =SUMPRODUCT(AA28:AA32,AE28:AE32) -> 13.511978
B34: Cash Per Share | G34: =IFERROR(G27/G45,"") -> 0.26014695 | H34: =IFERROR(H27/H45,"") -> 0.37557967 | I34: =IFERROR(I27/I45,"") -> 0.47011286 | J34: =IFERROR(J27/J45,"") -> 0.20723601 | K34: =IFERROR(K27/K45,"") -> 0.43492262 | L34: =IFERROR(L27/L45,"") -> 0.37424607 | M34: =IFERROR(M27/M45,"") -> 0.40597006 | N34: =IFERROR(N27/N45,"") -> 0.54660381 | ... Y34: =IFERROR(Y27/Y45,"") -> 2.4598942
B35: Tangible Book Value Per Share | G35: {=IF(_xldudf_WISE($E$2,$B35,G$13)="unavailable","",_xldudf_WISE($E$2,$B35,G$13))} -> 0.41495964 | H35: {=IF(_xldudf_WISE($E$2,$B35,H$13)="unavailable","",_xldudf_WISE($E$2,$B35,H$13))} -> 0.58635983 | I35: {=IF(_xldudf_WISE($E$2,$B35,I$13)="unavailable","",_xldudf_WISE($E$2,$B35,I$13))} -> 0.88334513 | J35: {=IF(_xldudf_WISE($E$2,$B35,J$13)="unavailable","",_xldudf_WISE($E$2,$B35,J$13))} -> 1.2472568 | K35: {=IF(_xldudf_WISE($E$2,$B35,K$13)="unavailable","",_xldudf_WISE($E$2,$B35,K$13))} -> 1.8342086 | L35: {=IF(_xldudf_WISE($E$2,$B35,L$13)="unavailable","",_xldudf_WISE($E$2,$B35,L$13))} -> 2.789223 | M35: {=IF(_xldudf_WISE($E$2,$B35,M$13)="unavailable","",_xldudf_WISE($E$2,$B35,M$13))} -> 4.3114155 | N35: {=IF(_xldudf_WISE($E$2,$B35,N$13)="unavailable","",_xldudf_WISE($E$2,$B35,N$13))} -> 4.5463654 | ... Y35: {=IF(_xldudf_WISE($E$2,$B35,Y$13)="unavailable","",_xldudf_WISE($E$2,$B35,Y$13))} -> 5.7887725 | AA35: Financial Leverage
B36: Debt To Equity | G36: {=_xldudf_WISE(E2,B36:B43,G13:Y13)} -> 0 | H36: 0 | I36: 0 | J36: 0 | K36: 0 | L36: 0 | M36: 0 | N36: 0.13727347 | O36: 0.31641371 | P36: 0.5389636 | Q36: 0.67861738 | R36: 0.86298089 | S36: 1.0684667 | T36: 1.1940478 | U36: 1.8714397 | V36: 2.1639246 | W36: 2.6144616 | X36: 1.994175 | Y36: 0.79547567 | AD36: =E11 -> 2023 | AE36: TTM
B37: Net Debt To EBITDA | G37: -2.3868559 | H37: -1.9796782 | I37: -1.6258215 | J37: -0.43752598 | K37: -0.58010509 | L37: -0.27249507 | M37: -0.1820122 | N37: 0.047346094 | O37: 0.34703056 | P37: 0.51130702 | Q37: 0.90747685 | R37: 1.2458175 | S37: 1.017508 | T37: 0.72322258 | U37: 1.0400148 | V37: 0.82495777 | W37: 0.81745257 | X37: 0.72735084 | Y37: 0.30176758 | AA37: Total Liabilities | AD37: {=_xldudf_WISE($E$2,$AA37:$AA40,AD$36:AE$36)/1000000} -> 290437 | AE37: 264591
B38: PE Ratio | G38: 32.675951 | H38: 37.958109 | I38: 23.387538 | J38: 19.766742 | K38: 18.971948 | L38: 14.416186 | M38: 14.946172 | N38: 12.060258 | O38: 15.519672 | P38: 12.361547 | Q38: 13.497731 | R38: 16.630087 | S38: 18.792325 | T38: 18.288816 | U38: 33.935934 | V38: 25.916254 | W38: 24.441824 | X38: 27.790812 | Y38: 39.505428 | AA38: Total Assets | AD38: 352583 | AE38: 371082
B39: PB Ratio | G39: 6.5096621 | H39: 9.1290662 | I39: 5.0704291 | J39: 5.1447256 | K39: 5.5628446 | L39: 4.8775875 | M39: 5.2766144 | N39: 3.6153735 | O39: 5.4970751 | P39: 5.5299942 | Q39: 4.808387 | R39: 5.998503 | S39: 10.441038 | T39: 11.167965 | U39: 29.81827 | V39: 38.892865 | W39: 48.14034 | X39: 43.374791 | Y39: 45.241008 | AA39: Total Equity | AD39: 62146 | AE39: 106491
B40: Current Ratio | G40: 2.2519013 | H40: 2.3659483 | I40: 2.6411407 | J40: 2.7424822 | K40: 2.0112923 | L40: 1.6084376 | M40: 1.4958487 | N40: 1.6786385 | O40: 1.0801128 | P40: 1.1087706 | Q40: 1.3526694 | R40: 1.2760628 | S40: 1.1329262 | T40: 1.5401256 | U40: 1.3636044 | V40: 1.0745531 | W40: 0.87935603 | X40: 0.98801167 | Y40: 1.0703575 | AA40: EBITDA | AD40: 129188 | AE40: 160332
B41: ROE | G41: 0.19921875 | H41: 0.24050372 | I41: 0.21680047 | J41: 0.26027181 | K41: 0.2932142 | L41: 0.33834106 | M41: 0.3530412 | N41: 0.2997758 | O41: 0.35420047 | P41: 0.44735453 | Q41: 0.3562367 | R41: 0.36070184 | S41: 0.55560118 | T41: 0.61064451 | U41: 0.87866359 | V41: 1.5007133 | W41: 1.9695887 | X41: 1.5607601 | Y41: 1.4668924
B42: Dividend | G42: 0 | H42: 0 | I42: 0 | J42: 0 | K42: 0 | L42: 0 | M42: 5.3 | N42: 11.8 | O42: 7.28 | P42: 2.03 | Q42: 2.23 | R42: 2.46 | S42: 2.82 | T42: 3.04 | U42: 2.615 | V42: 0.865 | W42: 0.91 | X42: 0.95 | Y42: 1.05 | AA42: Debt-to-Equity | AD42: =AD37/AD39 -> 4.6734625 | AE42: =AE37/AE39 -> 2.4846325
B43: Dividend Yield | G43: 0 | H43: 0 | I43: 0 | J43: 0 | K43: 0 | L43: 0 | M43: 0.0039887866 | N43: 0.023650264 | O43: 0.018144687 | P43: 0.017515805 | Q43: 0.01970257 | R43: 0.015880234 | S43: 0.0122568 | T43: 0.013971367 | U43: 0.0072273415 | V43: 0.0058958715 | W43: 0.0060839546 | X43: 0.0055739607 | Y43: 0.0032061069 | AA43: Debt-to-Assets | AD43: =AD37/AD38 -> 0.82374079 | AE43: =AE37/AE38 -> 0.71302569
B44: Dividends Yield Growth | H44: =IFERROR((H43-G43)/G43,"") | I44: =IFERROR((I43-H43)/H43,"") | J44: =IFERROR((J43-I43)/I43,"") | K44: =IFERROR((K43-J43)/J43,"") | L44: =IFERROR((L43-K43)/K43,"") | M44: =IFERROR((M43-L43)/L43,"") | N44: =IFERROR((N43-M43)/M43,"") -> 4.9291875 | O44: =IFERROR((O43-N43)/N43,"") -> -0.23279132 | ... Y44: =IFERROR((Y43-X43)/X43,"") -> -0.42480634
B45: Weighted Average Shs Out Dil | G45: {=_xldudf_WISE($E$2,$B45,G$13:Y$13)/1000000} -> 24570.728 | H45: 24900.176 | I45: 25259.892 | J45: 25396.165 | K45: 25891.962 | L45: 26226.06 | M45: 26469.932 | N45: 26086.536 | O45: 24490.652 | P45: 23172.276 | Q45: 22001.124 | R45: 21006.768 | S45: 20000.436 | T45: 18595.652 | U45: 17528.214 | V45: 16864.919 | W45: 16325.819 | X45: 15812.547 | Y45: 14768.115 | AA45: Net Debt-to-EBITDA | AD45: =(AD37-X27)/AD40 -> 2.0162244 | AE45: =(AE37-Y27)/AE40 -> 1.4236896
B46: Weighted Average Shares Dil Growth | H46: =IFERROR((H45-G45)/G45,"") -> 0.01340815 | I46: =IFERROR((I45-H45)/H45,"") -> 0.014446324 | J46: =IFERROR((J45-I45)/I45,"") -> 0.0053948527 | K46: =IFERROR((K45-J45)/J45,"") -> 0.019522494 | L46: =IFERROR((L45-K45)/K45,"") -> 0.012903546 | M46: =IFERROR((M45-L45)/L45,"") -> 0.0092988424 | N46: =IFERROR((N45-M45)/M45,"") -> -0.014484208 | O46: =IFERROR((O45-N45)/N45,"") -> -0.061176539 | ... Y46: =IFERROR((Y45-X45)/X45,"") -> -0.066050839 | AA46: Total Debt-to-EBITDA | AD46: =AD37/AD40 -> 2.2481732 | AE46: =AE37/AE40 -> 1.6502694

Sheet CHARTS
B2: Charts

Sheet FS
B2: Ticker | C2: AAPL
B4: Income Statement | G4: =H4-1 -> 2016 | H4: =I4-1 -> 2017 | I4: =J4-1 -> 2018 | J4: =K4-1 -> 2019 | K4: =L4-1 -> 2020 | L4: =M4-1 -> 2021 | M4: =N4-1 -> 2022 | N4: 2023 | P4: Key Metrics | U4: =G4 -> 2016 | V4: =H4 -> 2017 | W4: =I4 -> 2018 | X4: =J4 -> 2019 | Y4: =K4 -> 2020 | Z4: =L4 -> 2021 | AA4: =M4 -> 2022 | AB4: =N4 -> 2023 | AD4: Financial Growth | AI4: =U4 -> 2016 | AJ4: =V4 -> 2017 | AK4: =W4 -> 2018 | AL4: =X4 -> 2019 | AM4: =Y4 -> 2020 | AN4: =Z4 -> 2021 | AO4: =AA4 -> 2022 | AP4: =AB4 -> 2023 | AR4: Analyst Estimates | AW4: =AX4-1 -> 2023 | AX4: 2024
B5: (in millions $) | P5: Revenue Per Share | U5: {=_xldudf_WISE(C2,P5:P60,U4:AB4)} -> 9.854053 | V5: 10.984444 | W5: 13.399334 | X5: 14.085283 | Y5: 15.820258 | Z5: 21.903541 | AA5: 24.317273 | AB5: 24.344473 | AD5: Revenue Growth | AI5: {=_xldudf_WISE(C2,AD5:AD38,AI4:AP4)} -> -0.0773 | AJ5: 0.063 | AK5: 0.1586 | AL5: -0.0204 | AM5: 0.0551 | AN5: 0.3326 | AO5: 0.0779 | AP5: -0.028 | AR5: Estimated Revenue Low | AW5: {=_xldudf_WISE($C$2,$AR5:$AR19,AW$4:AX$4)/1000000} -> 366438.57 | AX5: 389950.95
B6: Revenue | G6: {=_xldudf_WISE($C$2,$B6:$B8,G$4:N$4)/1000000} -> 215639 | H6: 229234 | I6: 265595 | J6: 260174 | K6: 274515 | L6: 365817 | M6: 394328 | N6: 383285 | P6: Net Income Per Share | U6: 2.0877583 | V6: 2.3168851 | W6: 3.0033537 | X6: 2.9914458 | Y6: 3.3085873 | Z6: 5.6690293 | AA6: 6.1546144 | AB6: 6.1606693 | AD6: Gross Profit Growth | AI6: -0.1 | AJ6: 0.0466 | AK6: 0.1548 | AL6: -0.0338 | AM6: 0.0667 | AN6: 0.4562 | AO6: 0.1174 | AP6: -0.0096 | AR6: Estimated Revenue High | AW6: 401241.69 | AX6: 392209.91
B7: Cost Of Revenue | G7: 131376 | H7: 141048 | I7: 163756 | J7: 161782 | K7: 169559 | L7: 212981 | M7: 223546 | N7: 214137 | P7: Operating Cash Flow Per Share | U7: 3.0265573 | V7: 3.077536 | W7: 3.9065645 | X7: 3.7566855 | Y7: 4.6492304 | Z7: 6.2293459 | AA7: 7.5327626 | AB7: 7.0211749 | AD7: Ebitgrowth | AI7: -0.1423 | AJ7: 0.057 | AK7: 0.1465 | AL7: -0.0897 | AM7: 0.0094 | AN7: 0.5987 | AO7: 0.091 | AP7: -0.0358 | AR7: Estimated Revenue AVG | AW7: 381623 | AX7: 390480.7
B8: Gross Profit | G8: 84263 | H8: 88186 | I8: 101839 | J8: 98392 | K8: 104956 | L8: 152836 | M8: 170782 | N8: 169148 | P8: Free Cash Flow Per Share | U8: 2.4074545 | V8: 2.4644247 | W8: 3.2349204 | X8: 3.1885079 | Y8: 4.2280139 | Z8: 5.565624 | AA8: 6.8724256 | AB8: 6.3251104 | AD8: Operating Income Growth | AI8: -0.1573 | AJ8: 0.022 | AK8: 0.1557 | AL8: -0.0983 | AM8: 0.0369 | AN8: 0.6436 | AO8: 0.0963 | AP8: -0.043 | AR8: Estimated EBITDA Low | AW8: 132260.49 | AX8: 140746.93
B9: Gross Profit Ratio | G9: {=_xldudf_WISE($C$2,$B9,G$4:N$4)} -> 0.39075956 | H9: 0.38469861 | I9: 0.38343719 | J9: 0.37817768 | K9: 0.38233248 | L9: 0.4177936 | M9: 0.43309631 | N9: 0.4413113 | P9: Cash Per Share | U9: 3.0687813 | V9: 3.554608 | W9: 3.3449019 | X9: 5.4439484 | Y9: 5.2410314 | Z9: 3.7505527 | AA9: 2.9787932 | AB9: 3.909686 | AD9: Net Income Growth | AI9: -0.1443 | AJ9: 0.0583 | AK9: 0.2312 | AL9: -0.0718 | AM9: 0.039 | AN9: 0.6492 | AO9: 0.0541 | AP9: -0.0281 | AR9: Estimated EBITDA High | AW9: 144822.15 | AX9: 141562.27
P10: Book Value Per Share | U10: 5.8605931 | V10: 6.4232692 | W10: 5.4055928 | X10: 4.8988335 | Y10: 3.7654767 | Z10: 3.7775566 | AA10: 3.1248221 | AB10: 3.9472236 | AD10: Epsgrowth | AI10: -0.0991 | AJ10: 0.11 | AK10: 0.2931 | AL10: -0.0033 | AM10: 0.107 | AN10: 0.713 | AO10: 0.0847 | AP10: 0.0016 | AR10: Estimated EBITDA AVG | AW10: 137741.08 | AX10: 140938.13
B11: Research And Development Expenses | G11: {=_xldudf_WISE($C$2,$B11:$B14,G$4:N$4)/1000000} -> 10045 | H11: 11581 | I11: 14236 | J11: 16217 | K11: 18752 | L11: 21914 | M11: 26251 | N11: 29915 | P11: Tangible Book Value Per Share | U11: 5.4666851 | V11: 6.0392062 | W11: 5.4055928 | X11: 4.8988335 | Y11: 3.7654767 | Z11: 3.7775566 | AA11: 3.1248221 | AB11: 3.9472236 | AD11: Epsdiluted Growth | AI11: -0.0957 | AJ11: 0.1058 | AK11: 0.2957 | AL11: -0.0034 | AM11: 0.1044 | AN11: 0.7104 | AO11: 0.0891 | AP11: 0.0033 | AR11: Estimated EBIT Low | AW11: 122730.09 | AX11: 130605.02
B12: Selling General And Administrative Expenses | G12: 14194 | H12: 15261 | I12: 16705 | J12: 18245 | K12: 19916 | L12: 21973 | M12: 25094 | N12: 24932 | P12: Shareholders Equity Per Share | U12: 5.8605931 | V12: 6.4232692 | W12: 5.4055928 | X12: 4.8988335 | Y12: 3.7654767 | Z12: 3.7775566 | AA12: 3.1248221 | AB12: 3.9472236 | AD12: Weighted Average Shares Growth | AI12: -0.0491 | AJ12: -0.0464 | AK12: -0.0502 | AL12: -0.0681 | AM12: -0.0606 | AN12: -0.0375 | AO12: -0.0291 | AP12: -0.0291 | AR12: Estimated EBIT High | AW12: 134386.59 | AX12: 131361.6
B13: Other Expenses | G13: 0 | H13: 0 | I13: 0 | J13: 0 | K13: 0 | L13: 0 | M13: 0 | N13: 0 | P13: Interest Debt Per Share | U13: 4.0436351 | V13: 5.6544722 | W13: 5.9391546 | X13: 6.0430388 | Y13: 7.2124332 | Z13: 8.3327186 | AA13: 8.3504754 | AB13: 8.1212604 | AD13: Weighted Average Shares Diluted Growth | AI13: -0.0505 | AJ13: -0.0452 | AK13: -0.0479 | AL13: -0.0702 | AM13: -0.0574 | AN13: -0.0378 | AO13: -0.032 | AP13: -0.0314 | AR13: Estimated EBIT AVG | AW13: 127815.77 | AX13: 130782.45
B14: Operating Expenses | G14: 24239 | H14: 26842 | I14: 30941 | J14: 34462 | K14: 38668 | L14: 43887 | M14: 51345 | N14: 54847 | P14: Market Cap | U14: 616670830400 | V14: 804081337040 | W14: 1118725911520 | X14: 1010566792560 | Y14: 1948295921320 | Z14: 2453750882240 | AA14: 2439367314090 | AB14: 2695569789510 | AD14: Dividendsper Share Growth | AI14: 0.1052 | AJ14: 0.102 | AK14: 0.1306 | AL14: 0.1049 | AM14: 0.0616 | AN14: 0.0675 | AO14: 0.0566 | AP14: 0.0427 | AR14: Estimated Net Income Low | AW14: 91839.249 | AX14: 92114.285
P15: Enterprise Value | U15: 683218830400 | V15: 899472337040 | W15: 1207295911520 | X15: 1069769792560 | Y15: 2032557921320 | Z15: 2555332882240 | AA15: 2548201314090 | AB15: 2789534789510 | AD15: Operating Cash Flow Growth | AI15: -0.185 | AJ15: -0.0303 | AK15: 0.2057 | AL15: -0.1039 | AM15: 0.1626 | AN15: 0.2896 | AO15: 0.1741 | AP15: -0.095 | AR15: Estimated Net Income High | AW15: 103321.44 | AX15: 103094.72
B16: Cost And Expenses | G16: {=_xldudf_WISE(C2,B16:B17,G4:N4)/1000000} -> 155615 | H16: 167890 | I16: 194697 | J16: 196244 | K16: 208227 | L16: 256868 | M16: 274891 | N16: 268984 | P16: Pe Ratio | U16: 13.497731 | V16: 16.630087 | W16: 18.792325 | X16: 18.288816 | Y16: 33.935934 | Z16: 25.916254 | AA16: 24.441824 | AB16: 27.790812 | AD16: Free Cash Flow Growth | AI16: -0.245 | AJ16: -0.0238 | AK16: 0.2468 | AL16: -0.0815 | AM16: 0.2457 | AN16: 0.267 | AO16: 0.1989 | AP16: -0.1064 | AR16: Estimated Net Income AVG | AW16: 100389 | AX16: 97294
B17: EBITDA | G17: 73333 | H17: 76569 | I17: 87046 | J17: 81860 | K17: 81020 | L17: 123136 | M17: 133138 | N17: 129188 | P17: Price To Sales Ratio | U17: 2.859737 | V17: 3.5076879 | W17: 4.2121497 | X17: 3.8841959 | Y17: 7.0972294 | Z17: 6.7075912 | AA17: 6.1861377 | AB17: 7.0328079 | AD17: Ten YRevenue Growth Per Share | AI17: 11.0573 | AJ17: 10.0772 | AK17: 9.1837 | AL17: 7.2669 | AM17: 5.1765 | AN17: 4.2365 | AO17: 3.0669 | AP17: 2.6905 | AR17: Estimated SGA Expense Low | AW17: 23584.887 | AX17: 25098.202
B18: EBITDA Ratio | G18: {=_xldudf_WISE($C$2,$B18,G$4:N$4)} -> 0.34007299 | H18: 0.33402113 | I18: 0.3277396 | J18: 0.31463559 | K18: 0.2951387 | L18: 0.33660546 | M18: 0.33763263 | N18: 0.33705467 | P18: Pocfratio | U18: 9.3109092 | V18: 12.519756 | W18: 14.447477 | X18: 14.56337 | Y18: 24.150233 | Z18: 23.585141 | AA18: 19.970097 | AB18: 24.384808 | AD18: Five YRevenue Growth Per Share | AI18: 1.3558 | AJ18: 0.8371 | AK18: 1.0313 | AL18: 0.8757 | AM18: 0.5578 | AN18: 1.2228 | AO18: 1.2138 | AP18: 0.8168 | AR18: Estimated SGA Expense High | AW18: 25824.901 | AX18: 25243.594
B19: Interest Expense | G19: {=_xldudf_WISE($C$2,$B19:$B21,G$4:N$4)/1000000} -> 1456 | H19: 2323 | I19: 3240 | J19: 3576 | K19: 2873 | L19: 2645 | M19: 2931 | N19: 3933 | P19: Pfcf Ratio | U19: 11.70531 | V19: 15.634481 | W19: 17.447106 | X19: 17.158496 | Y19: 26.556204 | Z19: 26.397759 | AA19: 21.888924 | AB19: 27.068302 | AD19: Three YRevenue Growth Per Share | AI19: 0.4938 | AJ19: 0.4628 | AK19: 0.3194 | AL19: 0.4294 | AM19: 0.4402 | AN19: 0.6347 | AO19: 0.7264 | AP19: 0.5388 | AR19: Estimated SGA Expense AVG | AW19: 24562.195 | AX19: 25132.298
B20: Depreciation And Amortization | G20: 10505 | H20: 10157 | I20: 10903 | J20: 12547 | K20: 11056 | L20: 11284 | M20: 11104 | N20: 11519 | P20: Pb Ratio | U20: 4.808387 | V20: 5.998503 | W20: 10.441038 | X20: 11.167965 | Y20: 29.81827 | Z20: 38.892865 | AA20: 48.14034 | AB20: 43.374791 | AD20: Ten YOperating CFGrowth Per Share | AI20: 31.2201 | AJ20: 12.6203 | AK20: 9.0492 | AL20: 8.2464 | AM20: 5.3669 | AN20: 3.2956 | AO20: 2.877 | AP20: 2.3897 | AR20: Estimated EPS AVG | AW20: {=_xldudf_WISE($C$2,$AR20:$AR24,AW$4:AX$4)} -> 6.45457 | AX20: 6.70821
B21: Operating Income | G21: 60024 | H21: 61344 | I21: 70898 | J21: 63930 | K21: 66288 | L21: 108949 | M21: 119437 | N21: 114301 | P21: Ptb Ratio | U21: 4.808387 | V21: 5.998503 | W21: 10.441038 | X21: 11.167965 | Y21: 29.81827 | Z21: 38.892865 | AA21: 48.14034 | AB21: 43.374791 | AD21: Five YOperating CFGrowth Per Share | AI21: 1.0871 | AJ21: 0.584 | AK21: 0.886 | AL21: 0.5314 | AM21: 0.3166 | AN21: 1.0582 | AO21: 1.4477 | AP21: 0.7973 | AR21: Estimated EPS High | AW21: 6.88594 | AX21: 6.87083
B22: Operating Income Ratio | G22: {=_xldudf_WISE($C$2,$B22,G$4:N$4)} -> 0.2783541 | H22: 0.26760428 | I22: 0.26694027 | J22: 0.24572017 | K22: 0.24147314 | L22: 0.29782378 | M22: 0.30288744 | N22: 0.29821412 | P22: Ev To Sales | U22: 3.1683454 | V22: 3.9238173 | W22: 4.5456274 | X22: 4.1117475 | Y22: 7.404178 | Z22: 6.9852765 | AA22: 6.4621364 | AB22: 7.2779649 | AD22: Three YOperating CFGrowth Per Share | AI22: 0.4612 | AJ22: 0.2546 | AK22: 0.1063 | AL22: 0.2412 | AM22: 0.5107 | AN22: 0.5946 | AO22: 1.0052 | AP22: 0.5102 | AR22: Estimated EPS Low | AW22: 6.1207 | AX22: 6.13903
P23: Enterprise Value Over EBITDA | U23: 9.3166628 | V23: 11.747213 | W23: 13.869631 | X23: 13.068285 | Y23: 25.087113 | Z23: 20.752119 | AA23: 19.139549 | AB23: 21.592832 | AD23: Ten YNet Income Growth Per Share | AI23: 23.8071 | AJ23: 15.0483 | AK23: 14.3365 | AL23: 8.0831 | AM23: 5.0125 | AN23: 4.6597 | AO23: 2.8602 | AP23: 3.3097 | AR23: Number Analyst Estimated Revenue | AW23: 22 | AX23: 25
B24: Total Other Income Expenses Net | G24: {=_xldudf_WISE($C$2,$B24:$B25,G$4:N$4)/1000000} -> 1348 | H24: 2745 | I24: 2005 | J24: 1807 | K24: 803 | L24: 258 | M24: -334 | N24: -565 | P24: Ev To Operating Cash Flow | U24: 10.315696 | V24: 14.005019 | W24: 15.59129 | X24: 15.41655 | Y24: 25.194709 | Z24: 24.561534 | AA24: 20.861076 | AB24: 25.234839 | AD24: Five YNet Income Growth Per Share | AI24: 1.0843 | AJ24: 0.4531 | AK24: 1.101 | AL24: 0.843 | AM24: 0.4261 | AN24: 1.7154 | AO24: 1.6564 | AP24: 1.0513 | AR24: Number Analysts Estimated EPS | AW24: 24 | AX24: 26
B25: Income Before Tax | G25: 61372 | H25: 64089 | I25: 72903 | J25: 65737 | K25: 67091 | L25: 109207 | M25: 119103 | N25: 113736 | P25: Ev To Free Cash Flow | U25: 12.968488 | V25: 17.489254 | W25: 18.828401 | X25: 18.163709 | Y25: 27.704736 | Z25: 27.490591 | AA25: 22.865513 | AB25: 28.011877 | AD25: Three YNet Income Growth Per Share | AI25: 0.4605 | AJ25: 0.4274 | AK25: 0.2945 | AL25: 0.4329 | AM25: 0.428 | AN25: 0.8876 | AO25: 1.0574 | AP25: 0.862
B26: Income Before Tax Ratio | G26: {=_xldudf_WISE($C$2,$B26,G$4:N$4)} -> 0.28460529 | H26: 0.27957895 | I26: 0.27448935 | J26: 0.25266552 | K26: 0.2443983 | L26: 0.29852905 | M26: 0.30204043 | N26: 0.29674002 | P26: Earnings Yield | U26: 0.074086527 | V26: 0.060131976 | W26: 0.053213213 | X26: 0.054678227 | Y26: 0.02946729 | Z26: 0.038585824 | AA26: 0.040913478 | AB26: 0.035983116 | AD26: Ten YShareholders Equity Growth Per Share | AI26: 12.8729 | AJ26: 9.7004 | AK26: 4.9844 | AL26: 2.8715 | AM26: 1.0064 | AN26: 0.276 | AO26: -0.3081 | AP26: -0.1722
B27: Income Tax Expense | G27: {=_xldudf_WISE($C$2,$B27:$B28,G$4:N$4)/1000000} -> 15685 | H27: 15738 | I27: 13372 | J27: 10481 | K27: 9680 | L27: 14527 | M27: 19300 | N27: 16741 | P27: Free Cash Flow Yield | U27: 0.085431315 | V27: 0.063961191 | W27: 0.057316094 | X27: 0.058280166 | Y27: 0.037655984 | Z27: 0.037882004 | AA27: 0.045685207 | AB27: 0.036943581 | AD27: Five YShareholders Equity Growth Per Share | AI27: 0.9796 | AJ27: 0.4223 | AK27: 0.1336 | AL27: 0.069 | AM27: -0.274 | AN27: -0.3554 | AO27: -0.5135 | AP27: -0.2698
B28: Net Income | G28: 45687 | H28: 48351 | I28: 59531 | J28: 55256 | K28: 57411 | L28: 94680 | M28: 99803 | N28: 96995 | P28: Debt To Equity | U28: 0.67861738 | V28: 0.86298089 | W28: 1.0684667 | X28: 1.1940478 | Y28: 1.8714397 | Z28: 2.1639246 | AA28: 2.6144616 | AB28: 1.994175 | AD28: Three YShareholders Equity Growth Per Share | AI28: 0.229 | AJ28: 0.4017 | AK28: 0.0423 | AL28: -0.1641 | AM28: -0.4138 | AN28: -0.3012 | AO28: -0.3621 | AP28: 0.0483
P29: Debt To Assets | U29: 0.27054954 | V29: 0.30821781 | W29: 0.31303028 | X29: 0.31917841 | Y29: 0.37753174 | Z29: 0.38894935 | AA29: 0.37555811 | AB29: 0.35149171 | AD29: Ten YDividendper Share Growth Per Share | AI29: 0 | AJ29: 0 | AK29: 0 | AL29: 0 | AM29: 0 | AN29: 0 | AO29: 8.6284 | AP29: 1.3406
B30: Net Income Ratio | G30: {=_xldudf_WISE($C$2,$B30:$B32,G$4:N$4)} -> 0.21186798 | H30: 0.21092421 | I30: 0.22414202 | J30: 0.21238094 | K30: 0.20913611 | L30: 0.25881793 | M30: 0.25309641 | N30: 0.25306234 | P30: Net Debt To EBITDA | U30: 0.90747685 | V30: 1.2458175 | W30: 1.017508 | X30: 0.72322258 | Y30: 1.0400148 | Z30: 0.82495777 | AA30: 0.81745257 | AB30: 0.72735084 | AD30: Five YDividendper Share Growth Per Share | AI30: 0 | AJ30: 5.4371 | AK30: 0.6966 | AL30: 0.6724 | AM30: 0.6154 | AN30: 0.5601 | AO30: 0.4958 | AP30: 0.3795
B31: EPS | G31: 2.09 | H31: 2.32 | I31: 3 | J31: 2.99 | K31: 3.31 | L31: 5.67 | M31: 6.15 | N31: 6.16 | P31: Current Ratio | U31: 1.3526694 | V31: 1.2760628 | W31: 1.1329262 | X31: 1.5401256 | Y31: 1.3636044 | Z31: 1.0745531 | AA31: 0.87935603 | AB31: 0.98801167 | AD31: Three YDividendper Share Growth Per Share | AI31: 0.3617 | AJ31: 0.3387 | AK31: 0.3771 | AL31: 0.3767 | AM31: 0.3262 | AN31: 0.2522 | AO31: 0.1973 | AP31: 0.176
B32: EPS Diluted | G32: 2.08 | H32: 2.3 | I32: 2.98 | J32: 2.97 | K32: 3.28 | L32: 5.61 | M32: 6.11 | N32: 6.13 | P32: Interest Coverage | U32: 41.225275 | V32: 26.407232 | W32: 21.882099 | X32: 17.877517 | Y32: 23.072746 | Z32: 41.190548 | AA32: 40.749574 | AB32: 29.062039 | AD32: Receivables Growth | AI32: -0.0344 | AJ32: 0.2176 | AK32: 0.3734 | AL32: -0.0651 | AM32: -0.1825 | AN32: 0.3755 | AO32: 0.183 | AP32: 0.0009
B33: Weighted Average Shs Out | G33: {=_xldudf_WISE($C$2,$B33:$B34,G$4:N$4)/1000000} -> 21883.28 | H33: 20868.968 | I33: 19821.508 | J33: 18471.336 | K33: 17352.119 | L33: 16701.272 | M33: 16215.963 | N33: 15744.231 | P33: Income Quality | U33: 1.4496684 | V33: 1.3283076 | W33: 1.3007341 | X33: 1.2558093 | Y33: 1.4052011 | Z33: 1.0988382 | AA33: 1.2239211 | AB33: 1.1396773 | AD33: Asset Growth | AI33: 0.1079 | AJ33: 0.1667 | AK33: -0.0256 | AL33: -0.0744 | AM33: -0.0432 | AN33: 0.0837 | AO33: 0.005 | AP33: -0.0005
B34: Weighted Average Shs Out Dil | G34: 22001.124 | H34: 21006.768 | I34: 20000.436 | J34: 18595.652 | K34: 17528.214 | L34: 16864.919 | M34: 16325.819 | N34: 15812.547 | P34: Dividend Yield | U34: 0.01970257 | V34: 0.015880234 | W34: 0.0122568 | X34: 0.013971367 | Y34: 0.0072273415 | Z34: 0.0058958715 | AA34: 0.0060839546 | AB34: 0.0055739607 | AD34: Inventory Growth | AI34: -0.0924 | AJ34: 1.2772 | AK34: -0.1852 | AL34: 0.0379 | AM34: -0.011 | AN34: 0.6203 | AO34: -0.2483 | AP34: 0.28
P35: Payout Ratio | U35: 0.26593998 | V35: 0.26408968 | W35: 0.23033378 | X35: 0.25551976 | Y35: 0.24526659 | Z35: 0.1527989 | AA35: 0.14870294 | AB35: 0.15490489 | AD35: Book Valueper Share Growth | AI35: 0.13 | AJ35: 0.096 | AK35: -0.1584 | AL35: -0.0937 | AM35: -0.2314 | AN35: 0.0032 | AO35: -0.1728 | AP35: 0.2632
B36: Balance Sheet | G36: =G4 -> 2016 | H36: =H4 -> 2017 | I36: =I4 -> 2018 | J36: =J4 -> 2019 | K36: =K4 -> 2020 | L36: =L4 -> 2021 | M36: =M4 -> 2022 | N36: =N4 -> 2023 | P36: Sales General And Administrative To Revenue | U36: 0.065822973 | V36: 0.066573894 | W36: 0.062896515 | X36: 0.070126146 | Y36: 0.07254977 | Z36: 0.060065552 | AA36: 0.063637378 | AB36: 0.065048202 | AD36: Debt Growth | AI36: 0.3529 | AJ36: 0.3292 | AK36: -0.0103 | AL36: -0.0562 | AM36: 0.1317 | AN36: 0.1165 | AO36: -0.0296 | AP36: -0.0645
B37: (in millions $) | P37: Research And Ddevelopement To Revenue | U37: 0.046582483 | V37: 0.050520429 | W37: 0.053600407 | X37: 0.062331363 | Y37: 0.068309564 | Z37: 0.059904269 | AA37: 0.066571484 | AB37: 0.078048971 | AD37: Rdexpense Growth | AI37: 0.2452 | AJ37: 0.1529 | AK37: 0.2293 | AL37: 0.1392 | AM37: 0.1563 | AN37: 0.1686 | AO37: 0.1979 | AP37: 0.1396
B38: Cash And Cash Equivalents | G38: {=_xldudf_WISE($C$2,$B38:$B44,G$4:N$4)/1000000} -> 20484 | H38: 20289 | I38: 25913 | J38: 48844 | K38: 38016 | L38: 34940 | M38: 23646 | N38: 29965 | P38: Intangibles To Total Assets | U38: 0.026796317 | V38: 0.021355167 | W38: 0 | X38: 0 | Y38: 0 | Z38: 0 | AA38: 0 | AB38: 0 | AD38: Sgaexpenses Growth | AI38: -0.0094 | AJ38: 0.0752 | AK38: 0.0946 | AL38: 0.0922 | AM38: 0.0916 | AN38: 0.1033 | AO38: 0.142 | AP38: -0.0065
B39: Short Term Investments | G39: 46671 | H39: 53892 | I39: 40388 | J39: 51713 | K39: 52927 | L39: 27699 | M39: 24658 | N39: 31590 | P39: Capex To Operating Cash Flow | U39: 0.20455678 | V39: 0.19922149 | W39: 0.17192706 | X39: 0.1512444 | Y39: 0.090599202 | Z39: 0.10654761 | AA39: 0.087661992 | AB39: 0.099137892
B40: Cash And Short Term Investments | G40: 67155 | H40: 74181 | I40: 66301 | J40: 100557 | K40: 90943 | L40: 62639 | M40: 48304 | N40: 61555 | P40: Capex To Revenue | U40: 0.062827225 | V40: 0.055816327 | W40: 0.050125191 | X40: 0.040338389 | Y40: 0.026625139 | Z40: 0.030302036 | AA40: 0.027155059 | AB40: 0.028592301
B41: Net Receivables | G41: 29299 | H41: 35673 | I41: 48995 | J41: 45804 | K41: 37445 | L41: 51506 | M41: 60932 | N41: 60985 | P41: Capex To Depreciation | U41: 1.2896716 | V41: 1.2597224 | W41: 1.2210401 | X41: 0.83645493 | Y41: 0.661089 | Z41: 0.98236441 | AA41: 0.96433718 | AB41: 0.95138467
B42: Inventory | G42: 2132 | H42: 4855 | I42: 3956 | J42: 4106 | K42: 4061 | L42: 6580 | M42: 4946 | N42: 6331 | P42: Stock Based Compensation To Revenue | U42: 0.01952337 | V42: 0.021113796 | W42: 0.0201058 | X42: 0.023322853 | Y42: 0.024876601 | Z42: 0.021611899 | AA42: 0.022920006 | AB42: 0.028263564
B43: Other Current Assets | G43: 8283 | H43: 13936 | I43: 12087 | J43: 12352 | K43: 11264 | L43: 14111 | M43: 21223 | N43: 14695 | P43: Graham Number | U43: 16.592131 | V43: 18.298756 | W43: 19.112441 | X43: 18.158425 | Y43: 16.742586 | Z43: 21.950838 | AA43: 20.801964 | AB43: 23.391123
B44: Total Current Assets | G44: 106869 | H44: 128645 | I44: 131339 | J44: 162819 | K44: 143713 | L44: 134836 | M44: 135405 | N44: 143566 | P44: Roic | U44: 0.17572217 | V44: 0.15796434 | W44: 0.21399019 | X44: 0.21577874 | Y44: 0.24269487 | Z44: 0.38925056 | AA44: 0.45174761 | AB44: 0.43389183
P45: Return On Tangible Assets | U45: 0.14593408 | V45: 0.13163755 | W45: 0.16277531 | X45: 0.1632301 | Y45: 0.17725572 | Z45: 0.26974205 | AA45: 0.28292441 | AB45: 0.27509835
B46: Property Plant Equipment Net | G46: {=_xldudf_WISE($C$2,$B46:$B52,G$4:N$4)/1000000} -> 27010 | H46: 33783 | I46: 41304 | J46: 37378 | K46: 45336 | L46: 49527 | M46: 52534 | N46: 54376 | P46: Graham Net Net | U46: -4.7178371 | V46: -6.6083167 | W46: -7.7467744 | X46: -6.0128298 | Y46: -7.9236288 | Z46: -10.978415 | AA46: -12.679296 | AB46: -11.431346
B47: Goodwill | G47: 5414 | H47: 5717 | I47: 0 | J47: 0 | K47: 0 | L47: 0 | M47: 0 | N47: 0 | P47: Working Capital | U47: 27863000000 | V47: 27831000000 | W47: 15410000000 | X47: 57101000000 | Y47: 38321000000 | Z47: 9355000000 | AA47: -18577000000 | AB47: -1742000000
B48: Intangible Assets | G48: 3206 | H48: 2298 | I48: 0 | J48: 0 | K48: 0 | L48: 0 | M48: 0 | N48: 0 | P48: Tangible Asset Value | U48: 119629000000 | V48: 126032000000 | W48: 107147000000 | X48: 90488000000 | Y48: 65339000000 | Z48: 63090000000 | AA48: 50672000000 | AB48: 62146000000
B49: Long Term Investments | G49: 170430 | H49: 194714 | I49: 170799 | J49: 105341 | K49: 100887 | L49: 127877 | M49: 120805 | N49: 100544 | P49: Net Current Asset Value | U49: -86568000000 | V49: -112627000000 | W49: -127239000000 | X49: -85209000000 | Y49: -114836000000 | Z49: -153076000000 | AA49: -166678000000 | AB49: -146871000000
B50: Tax Assets | G50: 0 | H50: -8015 | I50: 0 | J50: 0 | K50: 0 | L50: 0 | M50: 15375 | N50: 17852 | P50: Average Receivables | U50: 29821000000 | V50: 32486000000 | W50: 42334000000 | X50: 47399500000 | Y50: 41624500000 | Z50: 44475500000 | AA50: 56219000000 | AB50: 60958500000
B51: Other Non Current Assets | G51: 8757 | H51: 18177 | I51: 22283 | J51: 32978 | K51: 33952 | L51: 38762 | M51: 28636 | N51: 36245 | P51: Average Payables | U51: 36392000000 | V51: 40768000000 | W51: 50065000000 | X51: 51062000000 | Y51: 44266000000 | Z51: 48529500000 | AA51: 59439000000 | AB51: 63363000000
B52: Total Non Current Assets | G52: 214817 | H52: 246674 | I52: 234386 | J52: 175697 | K52: 180175 | L52: 216166 | M52: 217350 | N52: 209017 | P52: Average Inventory | U52: 2240500000 | V52: 3493500000 | W52: 4405500000 | X52: 4031000000 | Y52: 4083500000 | Z52: 5320500000 | AA52: 5763000000 | AB52: 5638500000
P53: Days Sales Outstanding | U53: 49.592768 | V53: 56.800671 | W53: 67.332499 | X53: 64.258765 | Y53: 49.787534 | Z53: 51.390969 | AA53: 56.400205 | AB53: 58.075649
B54: Other Assets | G54: {=_xldudf_WISE($C$2,$B54:$B55,G$4:N$4)/1000000} -> 0 | H54: 0 | I54: 0 | J54: 0 | K54: 0 | L54: 0 | M54: 0 | N54: 0 | P54: Days Payables Outstanding | U54: 103.61337 | V54: 114.48819 | W54: 124.57021 | X54: 104.31408 | Y54: 91.04819 | Z54: 93.851071 | AA54: 104.68528 | AB54: 106.72147
B55: Total Assets | G55: 321686 | H55: 375319 | I55: 365725 | J55: 338516 | K55: 323888 | L55: 351002 | M55: 352755 | N55: 352583 | P55: Days Of Inventory On Hand | U55: 5.9233041 | V55: 12.563631 | W55: 8.8176311 | X55: 9.2636387 | Y55: 8.7418834 | Z55: 11.276593 | AA55: 8.0756981 | AB55: 10.791292
P56: Receivables Turnover | U56: 7.359944 | V56: 6.4259804 | W56: 5.4208593 | X56: 5.6801589 | Y56: 7.3311524 | Z56: 7.1024153 | AA56: 6.4716077 | AB56: 6.2849061
B57: Account Payables | G57: {=_xldudf_WISE($C$2,$B57:$B62,G$4:N$4)/1000000} -> 37294 | H57: 44242 | I57: 55888 | J57: 46236 | K57: 42296 | L57: 54763 | M57: 64115 | N57: 62611 | P57: Payables Turnover | U57: 3.5227114 | V57: 3.1881018 | W57: 2.9300744 | X57: 3.4990484 | Y57: 4.0088661 | Z57: 3.8891405 | AA57: 3.4866412 | AB57: 3.4201179
B58: Short Term Debt | G58: 11605 | H58: 18473 | I58: 20748 | J58: 16240 | K58: 15229 | L58: 17141 | M58: 22773 | N58: 17382 | P58: Inventory Turnover | U58: 61.621013 | V58: 29.052111 | W58: 41.394338 | X58: 39.401364 | Y58: 41.753016 | Z58: 32.367933 | AA58: 45.197331 | AB58: 33.823567
B59: Tax Payables | G59: 0 | H59: 0 | I59: 0 | J59: 0 | K59: 0 | L59: 0 | M59: 6552 | N59: 8819 | P59: Roe | U59: 0.3562367 | V59: 0.36070184 | W59: 0.55560118 | X59: 0.61064451 | Y59: 0.87866359 | Z59: 1.5007133 | AA59: 1.9695887 | AB59: 1.5607601
B60: Deferred Revenue | G60: 8080 | H60: 7548 | I60: 5966 | J60: 5522 | K60: 6643 | L60: 7612 | M60: 7912 | N60: 8061 | P60: Capex Per Share | U60: 0.6191028 | V60: 0.6131113 | W60: 0.67164416 | X60: 0.56817763 | Y60: 0.42121657 | Z60: 0.6637219 | AA60: 0.66033698 | AB60: 0.69606448
B61: Other Current Liabilities | G61: 22027 | H61: 30551 | I61: 33327 | J61: 37720 | K61: 41224 | L61: 45965 | M61: 52630 | N61: 48435
B62: Total Current Liabilities | G62: 79006 | H62: 100814 | I62: 115929 | J62: 105718 | K62: 105392 | L62: 125481 | M62: 153982 | N62: 145308
B64: Long Term Debt | G64: {=_xldudf_WISE($C$2,$B64:$B68,G$4:N$4)/1000000} -> 75427 | H64: 97207 | I64: 93735 | J64: 91807 | K64: 107049 | L64: 119381 | M64: 109707 | N64: 106548
B65: Deferred Revenue Non Current | G65: 2930 | H65: 2836 | I65: 2797 | J65: 0 | K65: 0 | L65: 0 | M65: 0 | N65: 0
B66: Deferred Tax Liabilities Non Current | G66: 26019 | H66: 31504 | I66: 426 | J66: 0 | K66: 0 | L66: 0 | M66: 0 | N66: 0
B67: Other Non Current Liabilities | G67: 10055 | H67: 8911 | I67: 45691 | J67: 50503 | K67: 46108 | L67: 43050 | M67: 38394 | N67: 38581
B68: Total Non Current Liabilities | G68: 114431 | H68: 140458 | I68: 142649 | J68: 142310 | K68: 153157 | L68: 162431 | M68: 148101 | N68: 145129
B70: Other Liabilities | G70: {=_xldudf_WISE($C$2,$B70:$B71,G$4:N$4)/1000000} -> 0 | H70: 0 | I70: 0 | J70: 0 | K70: 0 | L70: 0 | M70: 0 | N70: 0
B71: Total Liabilities | G71: 193437 | H71: 241272 | I71: 258578 | J71: 248028 | K71: 258549 | L71: 287912 | M71: 302083 | N71: 290437
B73: Common Stock | G73: {=_xldudf_WISE($C$2,$B73:$B77,G$4:N$4)/1000000} -> 31251 | H73: 35867 | I73: 40201 | J73: 45174 | K73: 50779 | L73: 57365 | M73: 64849 | N73: 73812
B74: Retained Earnings | G74: 96364 | H74: 98330 | I74: 70400 | J74: 45898 | K74: 14966 | L74: 5562 | M74: -3068 | N74: -214
B75: Accumulated Other Comprehensive Income Loss | G75: 634 | H75: -150 | I75: -3454 | J75: -584 | K75: -406 | L75: 163 | M75: -11109 | N75: -11452
B76: Othertotal Stockholders Equity | G76: 0 | H76: 0 | I76: 0 | J76: 0 | K76: 0 | L76: 0 | M76: 0 | N76: 0
B77: Total Stockholders Equity | G77: 128249 | H77: 134047 | I77: 107147 | J77: 90488 | K77: 65339 | L77: 63090 | M77: 50672 | N77: 62146
B79: Total Liabilities And Stockholders Equity | G79: {=_xldudf_WISE($C$2,$B79:$B82,G$4:N$4)/1000000} -> 321686 | H79: 375319 | I79: 365725 | J79: 338516 | K79: 323888 | L79: 351002 | M79: 352755 | N79: 352583
B80: Total Investments | G80: 217101 | H80: 248606 | I80: 211187 | J80: 157054 | K80: 153814 | L80: 155576 | M80: 145463 | N80: 132134
B81: Total Debt | G81: 87032 | H81: 115680 | I81: 114483 | J81: 108047 | K81: 122278 | L81: 136522 | M81: 132480 | N81: 123930
B82: Net Debt | G82: 66548 | H82: 95391 | I82: 88570 | J82: 59203 | K82: 84262 | L82: 101582 | M82: 108834 | N82: 93965
B84: Cash Flow Statement | G84: =G4 -> 2016 | H84: =H4 -> 2017 | I84: =I4 -> 2018 | J84: =J4 -> 2019 | K84: =K4 -> 2020 | L84: =L4 -> 2021 | M84: =M4 -> 2022 | N84: =N4 -> 2023
B85: (in millions $)
B86: Net Income | G86: {=_xldudf_WISE($C$2,$B86:$B96,G$4:N$4)/1000000} -> 45687 | H86: 48351 | I86: 59531 | J86: 55256 | K86: 57411 | L86: 94680 | M86: 99803 | N86: 96995
B87: Depreciation And Amortization | G87: 10505 | H87: 10157 | I87: 10903 | J87: 12547 | K87: 11056 | L87: 11284 | M87: 11104 | N87: 11519
B88: Deferred Income Tax | G88: 4938 | H88: 5966 | I88: -32590 | J88: -340 | K88: -215 | L88: -4774 | M88: 895 | N88: 0
B89: Stock Based Compensation | G89: 4210 | H89: 4840 | I89: 5340 | J89: 6068 | K89: 6829 | L89: 7906 | M89: 9038 | N89: 10833
B90: Change In Working Capital | G90: 405 | H90: -4923 | I90: 34694 | J90: -3488 | K90: 5690 | L90: -4911 | M90: 1200 | N90: -6577
B91: Accounts Receivables | G91: 476 | H91: -6347 | I91: -13332 | J91: 3176 | K91: 8470 | L91: -14028 | M91: -9343 | N91: -417
B92: Inventory | G92: 2132 | H92: 4855 | I92: 3956 | J92: 4106 | K92: 4061 | L92: 6580 | M92: 4946 | N92: 6331
B93: Accounts Payables | G93: 2117 | H93: 8966 | I93: 9175 | J93: -1923 | K93: -4062 | L93: 12326 | M93: 9448 | N93: -1889
B94: Other Working Capital | G94: -2405 | H94: -4819 | I94: 38023 | J94: -4452 | K94: 1409 | L94: -567 | M94: -389 | N94: -2653
B95: Other Non Cash Items | G95: 486 | H95: -166 | I95: -444 | J95: -652 | K95: -97 | L95: -147 | M95: 111 | N95: -2227
B96: Net Cash Provided By Operating Activities | G96: 66231 | H96: 64225 | I96: 77434 | J96: 69391 | K96: 80674 | L96: 104038 | M96: 122151 | N96: 110543
B98: Investments In Property Plant And Equipment | G98: {=_xldudf_WISE($C$2,$B98:$B103,G$4:N$4)/1000000} -> -13548 | H98: -12795 | I98: -13313 | J98: -10495 | K98: -7309 | L98: -11085 | M98: -10708 | N98: -10959
B99: Acquisitions Net | G99: -297 | H99: -329 | I99: -721 | J99: -624 | K99: -1524 | L99: -33 | M99: -306 | N99: 0
B100: Purchases Of Investments | G100: -143816 | H100: -160007 | I100: -73227 | J100: -40631 | K100: -114938 | L100: -109558 | M100: -76923 | N100: -29513
B101: Sales Maturities Of Investments | G101: 111794 | H101: 126465 | I101: 104072 | J101: 98724 | K101: 120391 | L101: 106483 | M101: 67363 | N101: 45514
B102: Other Investing Activites | G102: -924 | H102: -124 | I102: -745 | J102: -1078 | K102: -909 | L102: -352 | M102: -1780 | N102: -1337
B103: Net Cash Used For Investing Activites | G103: -45977 | H103: -46446 | I103: 16066 | J103: 45896 | K103: -4289 | L103: -14545 | M103: -22354 | N103: 3705
B105: Debt Repayment | G105: {=_xldudf_WISE($C$2,$B105:$B110,G$4:N$4)/1000000} -> 22057 | H105: 25162 | I105: 432 | J105: -7819 | K105: 2499 | L105: 12665 | M105: -123 | N105: -9901
B106: Common Stock Issued | G106: 495 | H106: 555 | I106: 669 | J106: 781 | K106: 880 | L106: 1105 | M106: 0 | N106: 0
B107: Common Stock Repurchased | G107: -29722 | H107: -32900 | I107: -72738 | J107: -66897 | K107: -72358 | L107: -85971 | M107: -89402 | N107: -77550
B108: Dividends Paid | G108: -12150 | H108: -12769 | I108: -13712 | J108: -14119 | K108: -14081 | L108: -14467 | M108: -14841 | N108: -15025
B109: Other Financing Activites | G109: -1570 | H109: 1978 | I109: -2527 | J109: -2922 | K109: -3760 | L109: -6685 | M109: -6383 | N109: -6012
...

Sheet DCF
B2: Ticker | C2: AAPL | E2: Current Price | G2: {=_xldudf_WISEPRICE(C2,"price")} -> 327.5
B4: Assumptions | S4: Switches | U4: Conservative case | W4: Base case | Y4: Optimistic case
B5: Switches | I5: Conservative case | K5: Base case | M5: Optimistic case | P5: Share Price | S5: =S17 -> 173.48114 | U5: =U17 -> 132.91787 | W5: =W17 -> 200.36151 | Y5: =Y17 -> 318.58736
B6: Revenue growth | D6: 2 | G6: Revenue 2022 | I6: =M22-1% -> 0.0087737631 | M6: =M22+1% -> 0.028773763 | P6: Upside (Downside) | S6: =S5/$G$2-1 -> -0.4702866 | U6: =U5/$G$2-1 -> -0.5941439 | W6: =W5/$G$2-1 -> -0.38820914 | Y6: =Y5/$G$2-1 -> -0.027214168
B7: EBIT margin | D7: 2 | G7: Revenue 2028 | I7: =K7-1% -> 0.04 | K7: 0.05 | M7: =K7+1% -> 0.06
B8: Taxes | D8: 2 | G8: EBIT 2022 | I8: =M25-1% -> 0.32492679 | M8: =M25+1% -> 0.34492679 | P8: DCF Valuation
B9: D&A | D9: 2 | G9: Taxes 2024 | I9: =M28+3% -> 0.17713108 | M9: =M28-3% -> 0.11713108 | S9: Switches | U9: Conservative case | W9: Base case | Y9: Optimistic case
B10: CapEx | D10: 1 | G10: D&A | I10: =M33-0.5% -> 0.024686226 | M10: =M33+0.5% -> 0.034686226 | P10: Terminal value | S10: =(S89*(1+D17))/(D16-D17) -> 1974823.3 | U10: =(S90*(1+I13))/(I12-I13) -> 1455289.3 | W10: =(S91*(1+K13))/(K12-K13) -> 2333037.4 | Y10: =(S92*(1+M13))/(M12-M13) -> 3935554.5
B11: WACC | D11: 2 | G11: CapEx (2028) | I11: =K11+2% -> 0.09 | K11: 0.07 | M11: =K11-2% -> 0.05 | P11: PV of terminal value | S11: =S10/(1+D16)^S94 -> 1077390.3 | U11: =U10/(1+I12)^S94 -> 744803.07 | W11: =W10/(1+K12)^S94 -> 1272818.6 | Y11: =W10/(1+M12)^S94 -> 1357609.5
B12: TGR | D12: 1 | G12: WACC | I12: =K12+1% -> 0.10041947 | K12: =Z27 -> 0.090419471 | M12: =K12-1% -> 0.080419471 | P12: Enterprise value | S12: =SUM(M95:S95)+S10 -> 2567886.4 | U12: =SUM(M96:S96)+U10 -> 1968843.4 | W12: =SUM(M97:S97)+W10 -> 2964858.8 | Y12: =SUM(M98:S98)+Y10 -> 4710831.8
G13: TGR | I13: =K13-0.5% -> 0.025 | K13: 0.03 | M13: =K13+0.5% -> 0.035 | P13: (+) Cash | S13: {=_xldudf_WISE(C2,"Cash and Short Term Investments","TTM")/1000000} -> 68507 | U13: {=_xldudf_WISE(C2,"Cash and Short Term Investments","TTM")/1000000} -> 68507 | W13: {=_xldudf_WISE(C2,"Cash and Short Term Investments","TTM")/1000000} -> 68507 | Y13: {=_xldudf_WISE(C2,"Cash and Short Term Investments","TTM")/1000000} -> 68507
P14: (-) Debt | S14: {=_xldudf_WISE(C2,"Long term debt","TTM")/1000000} -> 74404 | U14: {=_xldudf_WISE(C2,"Long term debt","TTM")/1000000} -> 74404 | W14: {=_xldudf_WISE(C2,"Long term debt","TTM")/1000000} -> 74404 | Y14: {=_xldudf_WISE(C2,"Long term debt","TTM")/1000000} -> 74404
B15: Valuation assumptions | G15: Risk-free rate | I15: =3.44% -> 0.0344 | P15: Equity value | S15: =S12+S13-S14 -> 2561989.4 | U15: =U12+U13-U14 -> 1962946.4 | W15: =W12+W13-W14 -> 2958961.8 | Y15: =Y12+Y13-Y14 -> 4704934.8
B16: WACC | D16: =CHOOSE(D11,I12,K12,M12) -> 0.090419471 | G16: Equity risk premium | I16: 0.09 | P16: Diluted shares outstanding | S16: =I17 -> 14768.115 | U16: =I17 -> 14768.115 | W16: =I17 -> 14768.115 | Y16: =I17 -> 14768.115
B17: TGR | D17: =CHOOSE(D12,I13,K13,M13) -> 0.025 | G17: Dil Shs outstanding | I17: {=_xldudf_WISE(C2,"Weighted Average Shs Out Dil","TTM")/1000000} -> 14768.115 | P17: Share price | S17: =S15/S16 -> 173.48114 | U17: =U15/U16 -> 132.91787 | W17: =W15/W16 -> 200.36151 | Y17: =Y15/Y16 -> 318.58736
B19: Income Statement | E19: 2014 | F19: =G19-1 -> 2017 | G19: =H19-1 -> 2018 | H19: =I19-1 -> 2019 | I19: =J19-1 -> 2020 | J19: =K19-1 -> 2021 | K19: =L19-1 -> 2022 | L19: 2023 | M19: =L19+1 -> 2024 | N19: =M19+1 -> 2025 | P19: WACC
B21: Revenue | E21: {=_xldudf_WISE($C$2,$B21,E$19)/1000000} -> 182795 | F21: {=_xldudf_WISE($C$2,$B21,F$19:L$19)/1000000} -> 229234 | G21: 265595 | H21: 260174 | I21: 274515 | J21: 365817 | K21: 394328 | L21: 383285 | M21: {=_xldudf_WISE($C$2,"Estimated Revenue AVG",M19)/1000000} -> 390480.7 | N21: {=_xldudf_WISE($C$2,"Estimated Revenue AVG",N19)/1000000} -> 415406.88 | P21: Cost of Debt | T21: Cost of Equity | W21: Weight of Debt and Equity
B22: % of growth | F22: =F21/E21-1 -> 0.25404962 | G22: =G21/F21-1 -> 0.15861958 | H22: =H21/G21-1 -> -0.020410776 | I22: =I21/H21-1 -> 0.055120804 | J22: =J21/I21-1 -> 0.33259385 | K22: =K21/J21-1 -> 0.077937876 | L22: =L21/K21-1 -> -0.028004605 | M22: =M21/L21-1 -> 0.018773763 | N22: =N21/M21-1 -> 0.063834603 | P22: Interest expense | S22: {=_xldudf_WISE(C2,"interest expense","TTM")/1000000} -> 0 | T22: Risk-free rate | V22: =I15 -> 0.0344 | W22: Total debt | Y22: =S23 -> 264591 | Z22: =Y22/Y24 -> 0.052139239
P23: Total debt | S23: {=_xldudf_WISE(C2,"total liabilities","TTM")/1000000} -> 264591 | T23: Beta | V23: {=_xldudf_WISEPRICE(C2,"beta")} -> 1.097 | W23: Market cap | Y23: {=_xldudf_WISEPRICE(C2,"Market Cap")/1000000} -> 4810109.1 | Z23: =Y23/Y24 -> 0.94786076
B24: EBIT | E24: {=_xldudf_WISE($C$2,"Operating income",E$19)/1000000} -> 52503 | F24: {=_xldudf_WISE($C$2,"Operating income",F$19:L$19)/1000000} -> 61344 | G24: 70898 | H24: 63930 | I24: 66288 | J24: 108949 | K24: 119437 | L24: 114301 | M24: {=_xldudf_WISE($C$2,"Estimated EBIT AVG",M19)/1000000} -> 130782.45 | N24: {=_xldudf_WISE($C$2,"Estimated EBIT AVG",N19)/1000000} -> 139130.89 | P24: Cost of debt | S24: =S22/S23 -> 0 | T24: Market return | V24: =I16 -> 0.09 | W24: Total | Y24: =SUM(Y22:Y23) -> 5074700.1
B25: % of revenue | F25: =F24/F21 -> 0.26760428 | G25: =G24/G21 -> 0.26694027 | H25: =H24/H21 -> 0.24572017 | I25: =I24/I21 -> 0.24147314 | J25: =J24/J21 -> 0.29782378 | K25: =K24/K21 -> 0.30288744 | L25: =L24/L21 -> 0.29821412 | M25: =M24/M21 -> 0.33492679 | N25: =N24/N21 -> 0.33492679 | P25: Income tax expense | S25: {=_xldudf_WISE(C2,"income tax expense","TTM")/1000000} -> 25095 | T25: Cost of equity | V25: =(V22)+(V23)*(V24-V22) -> 0.0953932
P26: Income before tax | S26: {=_xldudf_WISE(C2,"Income Before Tax","TTM")/1000000} -> 147670
B27: Taxes | E27: {=_xldudf_WISE($C$2,"Income Tax expense",E$19)/1000000} -> 13973 | F27: {=_xldudf_WISE($C$2,"Income Tax expense",F$19:L$19)/1000000} -> 15738 | G27: 13372 | H27: 10481 | I27: 9680 | J27: 14527 | K27: 19300 | L27: 16741 | M27: =M24*M28 -> 19242.163 | N27: =N24*N28 -> 21110.178 | P27: Effective tax rate | S27: =S25/S26 -> 0.16993973 | W27: WACC | Z27: =(S24*Z22)+(V25*Z23) -> 0.090419471
B28: % of EBIT | F28: =F27/F24 -> 0.25655321 | G28: =G27/G24 -> 0.18860899 | H28: =H27/H24 -> 0.16394494 | I28: =I27/I24 -> 0.14602945 | J28: =J27/J24 -> 0.13333762 | K28: =K27/K24 -> 0.16159147 | L28: =L27/L24 -> 0.14646416 | M28: =AVERAGE(J28:L28) -> 0.14713108 | N28: =AVERAGE(K28:M28) -> 0.1517289 | P28: Cost of debt after tax | S28: =S24*(1-S27) -> 0
B30: Cash Flow Items | F30: =F19 -> 2017 | G30: =G19 -> 2018 | H30: =H19 -> 2019 | I30: =I19 -> 2020 | J30: =J19 -> 2021 | K30: =K19 -> 2022 | L30: =L19 -> 2023 | M30: =M19 -> 2024 | N30: =N19 -> 2025
B32: D&A | F32: {=_xldudf_WISE($C$2,"Depreciation And Amortization",F30:L30)/1000000} -> 10157 | G32: 10903 | H32: 12547 | I32: 11056 | J32: 11284 | K32: 11104 | L32: 11519 | M32: =M21*M33 -> 11591.898 | N32: =N21*N33 -> 12171.266 | Q32: =S4 -> Switches | R32: =U4 -> Conservative case | S32: =W4 -> Base case | T32: =Y4 -> Optimistic case
B33: % of revenue | F33: =F32/F21 -> 0.044308436 | G33: =G32/G21 -> 0.041051225 | H33: =H32/H21 -> 0.048225418 | I33: =I32/I21 -> 0.040274666 | J33: =J32/J21 -> 0.030846024 | K33: =K32/K21 -> 0.028159299 | L33: =L32/L21 -> 0.030053355 | M33: =AVERAGE(J33:L33) -> 0.029686226 | N33: =AVERAGE(K33:M33) -> 0.029299626 | Q33: =S5 -> 173.48114 | R33: =U5 -> 132.91787 | S33: =W5 -> 200.36151 | T33: =Y5 -> 318.58736
B34: % of CapEx | F34: =F32/F36 -> 0.79382571 | G34: =G32/G36 -> 0.81897394 | H34: =H32/H36 -> 1.1955217 | I34: =I32/I36 -> 1.5126556 | J34: =J32/J36 -> 1.0179522 | K34: =K32/K36 -> 1.0369817 | L34: =L32/L36 -> 1.0510996 | M34: =M32/M36 -> 1.0349716 | N34: =N32/N36 -> 1.0410798 | Q34: =G2 -> 327.5 | R34: =Q34 -> 327.5 | S34: =R34 -> 327.5 | T34: =S34 -> 327.5
B36: CapEx | F36: {=-_xldudf_WISE($C$2,"Capital Expenditure",F30:L30)/1000000} -> 12795 | G36: 13313 | H36: 10495 | I36: 7309 | J36: 11085 | K36: 10708 | L36: 10959 | M36: =M21*M37 -> 11200.209 | N36: =N21*N37 -> 11691.002
B37: % of revenue | F37: =F36/F21 -> 0.055816327 | G37: =G36/G21 -> 0.050125191 | H37: =H36/H21 -> 0.040338389 | I37: =I36/I21 -> 0.026625139 | J37: =J36/J21 -> 0.030302036 | K37: =K36/K21 -> 0.027155059 | L37: =L36/L21 -> 0.028592301 | M37: =AVERAGE(J37:L37) -> 0.028683132 | N37: =AVERAGE(K37:M37) -> 0.028143497
B39: Change in NWC | F39: {=_xldudf_WISE($C$2,"Change In Working Capital",F30:L30)/1000000} -> -4923 | G39: 34694 | H39: -3488 | I39: 5690 | J39: -4911 | K39: 1200 | L39: -6577 | M39: =M40*M21 -> -3584.7623 | N39: =N40*N21 -> -3225.8817
B40: % of revenue | F40: =F39/F21 -> -0.021475872 | G40: =G39/G21 -> 0.13062746 | H40: =H39/H21 -> -0.013406413 | I40: =I39/I21 -> 0.020727465 | J40: =J39/J21 -> -0.013424745 | K40: =K39/K21 -> 0.0030431519 | L40: =L39/L21 -> -0.017159555 | M40: =AVERAGE(J40:L40) -> -0.0091803827 | N40: =AVERAGE(K40:M40) -> -0.0077655952
B41: % of change in revenue | G41: =G39/(G21-F21) -> 0.95415418 | H41: =H39/(H21-G21) -> 0.64342372 | I41: =I39/(I21-H21) -> 0.39676452 | J41: =J39/(J21-I21) -> -0.053788526 | K41: =K39/(K21-J21) -> 0.042089018 | L41: =L39/(L21-K21) -> 0.59558091 | M41: =M39/(M21-L21) -> -0.49818105 | N41: =N39/(N21-M21) -> -0.12941741
B43: DCF | F43: =F19 -> 2017 | G43: =G19 -> 2018 | H43: =H19 -> 2019 | I43: =I19 -> 2020 | J43: =J19 -> 2021 | K43: =K19 -> 2022 | L43: =L19 -> 2023 | M43: =M19 -> 2024 | N43: =M43+1 -> 2025 | O43: =N43+1 -> 2026 | P43: =O43+1 -> 2027 | Q43: =P43+1 -> 2028 | R43: =Q43+1 -> 2029 | S43: =R43+1 -> 2030
B45: Revenue | F45: =F21 -> 229234 | G45: =G21 -> 265595 | H45: =H21 -> 260174 | I45: =I21 -> 274515 | J45: =J21 -> 365817 | K45: =K21 -> 394328 | L45: =L21 -> 383285 | M45: =L45*(1+M46) -> 390480.7 | N45: =M45*(1+N46) -> 415406.88 | O45: =N45*(1+O46) -> 440487.47 | P45: =O45*(1+P46) -> 465558.83 | Q45: =P45*(1+Q46) -> 490446.97 | R45: =Q45*(1+R46) -> 514969.32 | S45: =R45*(1+S46) -> 540717.79
B46: % of growth | F46: =F22 -> 0.25404962 | G46: =G22 -> 0.15861958 | H46: =H22 -> -0.020410776 | I46: =I22 -> 0.055120804 | J46: =J22 -> 0.33259385 | K46: =K22 -> 0.077937876 | L46: =L22 -> -0.028004605 | M46: =OFFSET(M46,$D$6,0) -> 0.018773763 | N46: =OFFSET(N46,$D$6,0) -> 0.063834603 | O46: =OFFSET(O46,$D$6,0) -> 0.060375952 | P46: =OFFSET(P46,$D$6,0) -> 0.056917302 | Q46: =OFFSET(Q46,$D$6,0) -> 0.053458651 | R46: =OFFSET(R46,$D$6,0) -> 0.05 | S46: =OFFSET(S46,$D$6,0) -> 0.05
B47: Conservative case | M47: =I6 -> 0.0087737631 | N47: =N48-1% -> 0.053834603 | O47: =N47-(($N$47-$S$47)/($S$43-$O$43)) -> 0.050375952 | P47: =O47-(($N$47-$S$47)/($S$43-$O$43)) -> 0.046917302 | Q47: =P47-(($N$47-$S$47)/($S$43-$O$43)) -> 0.043458651 | R47: =Q47-(($N$47-$S$47)/($S$43-$O$43)) -> 0.04 | S47: =I7 -> 0.04
B48: Base case (Wall Street Estimates) | M48: =M22 -> 0.018773763 | N48: =N22 -> 0.063834603 | O48: =N48-(($N$48-$S$48)/($S$43-$O$43)) -> 0.060375952 | P48: =O48-(($N$48-$S$48)/($S$43-$O$43)) -> 0.056917302 | Q48: =P48-(($N$48-$S$48)/($S$43-$O$43)) -> 0.053458651 | R48: =Q48-(($N$48-$S$48)/($S$43-$O$43)) -> 0.05 | S48: =K7 -> 0.05
B49: Optimistic case | M49: =M6 -> 0.028773763 | N49: =N48+1% -> 0.073834603 | O49: =N49-(($N$49-$S$49)/($S$43-$O$43)) -> 0.070375952 | P49: =O49-(($N$49-$S$49)/($S$43-$O$43)) -> 0.066917302 | Q49: =P49-(($N$49-$S$49)/($S$43-$O$43)) -> 0.063458651 | R49: =Q49-(($N$49-$S$49)/($S$43-$O$43)) -> 0.06 | S49: =M7 -> 0.06
B50: Conservative case | M50: =$L$45*(1+M47) -> 386647.85 | N50: =M50*(1+N47) -> 407462.89 | O50: =N50*(1+O47) -> 427989.22 | P50: =O50*(1+P47) -> 448069.32 | Q50: =P50*(1+Q47) -> 467541.8 | R50: =Q50*(1+R47) -> 486243.48 | S50: =R50*(1+S47) -> 505693.21
B51: Base case (Wall Street Estimates) | M51: =$L$45*(1+M48) -> 390480.7 | N51: =M51*(1+N48) -> 415406.88 | O51: =N51*(1+O48) -> 440487.47 | P51: =O51*(1+P48) -> 465558.83 | Q51: =P51*(1+Q48) -> 490446.97 | R51: =Q51*(1+R48) -> 514969.32 | S51: =R51*(1+S48) -> 540717.79
B52: Optimistic case | M52: =$L$45*(1+M49) -> 394313.55 | N52: =M52*(1+N49) -> 423427.54 | O52: =N52*(1+O49) -> 453226.65 | P52: =O52*(1+P49) -> 483555.36 | Q52: =P52*(1+Q49) -> 514241.13 | R52: =Q52*(1+R49) -> 545095.6 | S52: =R52*(1+S49) -> 577801.33
B54: EBIT | F54: =F24 -> 61344 | G54: =G24 -> 70898 | H54: =H24 -> 63930 | I54: =I24 -> 66288 | J54: =J24 -> 108949 | K54: =K24 -> 119437 | L54: =L24 -> 114301 | M54: =M45*M55 -> 130782.45 | N54: =N45*N55 -> 139130.89 | O54: =O45*O55 -> 147531.05 | P54: =P45*P55 -> 155928.12 | Q54: =Q45*Q55 -> 164263.83 | R54: =R45*R55 -> 172477.02 | S54: =S45*S55 -> 181100.87
B55: % of revenue | F55: =F25 -> 0.26760428 | G55: =G25 -> 0.26694027 | H55: =H25 -> 0.24572017 | I55: =I25 -> 0.24147314 | J55: =J25 -> 0.29782378 | K55: =K25 -> 0.30288744 | L55: =L25 -> 0.29821412 | M55: =OFFSET(M55,$D$7,0) -> 0.33492679 | N55: =OFFSET(N55,$D$7,0) -> 0.33492679 | O55: =OFFSET(O55,$D$7,0) -> 0.33492679 | P55: =OFFSET(P55,$D$7,0) -> 0.33492679 | Q55: =OFFSET(Q55,$D$7,0) -> 0.33492679 | R55: =OFFSET(R55,$D$7,0) -> 0.33492679 | S55: =OFFSET(S55,$D$7,0) -> 0.33492679
B56: Conservative case | M56: =I8 -> 0.32492679 | N56: =M56 -> 0.32492679 | O56: =N56 -> 0.32492679 | P56: =O56 -> 0.32492679 | Q56: =P56 -> 0.32492679 | R56: =Q56 -> 0.32492679 | S56: =R56 -> 0.32492679
B57: Base case (Wall Street Estimates) | M57: =M25 -> 0.33492679 | N57: =N25 -> 0.33492679 | O57: =N57 -> 0.33492679 | P57: =O57 -> 0.33492679 | Q57: =P57 -> 0.33492679 | R57: =Q57 -> 0.33492679 | S57: =R57 -> 0.33492679
B58: Optimistic case | M58: =M8 -> 0.34492679 | N58: =M58 -> 0.34492679 | O58: =N58 -> 0.34492679 | P58: =O58 -> 0.34492679 | Q58: =P58 -> 0.34492679 | R58: =Q58 -> 0.34492679 | S58: =R58 -> 0.34492679
B60: Taxes | F60: =F27 -> 15738 | G60: =G27 -> 13372 | H60: =H27 -> 10481 | I60: =I27 -> 9680 | J60: =J27 -> 14527 | K60: =K27 -> 19300 | L60: =L27 -> 16741 | M60: =M54*M61 -> 19242.163 | N60: =N54*N61 -> 21110.178 | O60: =O54*O61 -> 22384.725 | P60: =P54*P61 -> 23658.803 | Q60: =Q54*Q61 -> 24923.571 | R60: =R54*R61 -> 26169.749 | S60: =S54*S61 -> 27478.237
B61: % of EBIT | F61: =F28 -> 0.25655321 | G61: =G28 -> 0.18860899 | H61: =H28 -> 0.16394494 | I61: =I28 -> 0.14602945 | J61: =J28 -> 0.13333762 | K61: =K28 -> 0.16159147 | L61: =L28 -> 0.14646416 | M61: =OFFSET(M61,$D$8,0) -> 0.14713108 | N61: =OFFSET(N61,$D$8,0) -> 0.1517289 | O61: =OFFSET(O61,$D$8,0) -> 0.1517289 | P61: =OFFSET(P61,$D$8,0) -> 0.1517289 | Q61: =OFFSET(Q61,$D$8,0) -> 0.1517289 | R61: =OFFSET(R61,$D$8,0) -> 0.1517289 | S61: =OFFSET(S61,$D$8,0) -> 0.1517289
B62: Conservative case | M62: =M63 -> 0.14713108 | N62: =N63 -> 0.1517289 | O62: =I9 -> 0.17713108 | P62: =O62 -> 0.17713108 | Q62: =P62 -> 0.17713108 | R62: =Q62 -> 0.17713108 | S62: =R62 -> 0.17713108
B63: Base case | M63: =M28 -> 0.14713108 | N63: =N28 -> 0.1517289 | O63: =N63 -> 0.1517289 | P63: =O63 -> 0.1517289 | Q63: =P63 -> 0.1517289 | R63: =Q63 -> 0.1517289 | S63: =R63 -> 0.1517289
B64: Optimistic case | M64: =M63 -> 0.14713108 | N64: =N63 -> 0.1517289 | O64: =M9 -> 0.11713108 | P64: =O64 -> 0.11713108 | Q64: =P64 -> 0.11713108 | R64: =Q64 -> 0.11713108 | S64: =R64 -> 0.11713108
B66: EBIAT | M66: =M54-M60 -> 111540.28 | N66: =N54-N60 -> 118020.72 | O66: =O54-O60 -> 125146.33 | P66: =P54-P60 -> 132269.32 | Q66: =Q54-Q60 -> 139340.26 | R66: =R54-R60 -> 146307.27 | S66: =S54-S60 -> 153622.64
B67: Conservative case | M67: =(M56*M50)-(M62*(M56*M50)) -> 107147.84 | N67: =(N56*N50)-(N62*(N56*N50)) -> 112307.37 | O67: =(O56*O50)-(O62*(O56*O50)) -> 114432.4 | P67: =(P56*P50)-(P62*(P56*P50)) -> 119801.26 | Q67: =(Q56*Q50)-(Q62*(Q56*Q50)) -> 125007.66 | R67: =(R56*R50)-(R62*(R56*R50)) -> 130007.97 | S67: =(S56*S50)-(S62*(S56*S50)) -> 135208.28
B68: Base case | M68: =(M57*M51)-(M63*(M57*M51)) -> 111540.28 | N68: =(N57*N51)-(N63*(N57*N51)) -> 118020.72 | O68: =(O57*O51)-(O63*(O57*O51)) -> 125146.33 | P68: =(P57*P51)-(P63*(P57*P51)) -> 132269.32 | Q68: =(Q57*Q51)-(Q63*(Q57*Q51)) -> 139340.26 | R68: =(R57*R51)-(R63*(R57*R51)) -> 146307.27 | S68: =(S57*S51)-(S63*(S57*S51)) -> 153622.64
B69: Optimistic case | M69: =(M58*M52)-(M64*(M58*M52)) -> 115998.11 | N69: =(N58*N52)-(N64*(N58*N52)) -> 123891.27 | O69: =(O58*O52)-(O64*(O58*O52)) -> 138018.91 | P69: =(P58*P52)-(P64*(P58*P52)) -> 147254.76 | Q69: =(Q58*Q52)-(Q64*(Q58*Q52)) -> 156599.35 | R69: =(R58*R52)-(R64*(R58*R52)) -> 165995.31 | S69: =(S58*S52)-(S64*(S58*S52)) -> 175955.03
B71: D&A | F71: =F32 -> 10157 | G71: =G32 -> 10903 | H71: =H32 -> 12547 | I71: =I32 -> 11056 | J71: =J32 -> 11284 | K71: =K32 -> 11104 | L71: =L32 -> 11519 | M71: =M45*M72 -> 11591.898 | N71: =N45*N72 -> 12171.266 | O71: =O45*O72 -> 12906.118 | P71: =P45*P72 -> 13640.7 | Q71: =Q45*Q72 -> 14369.913 | R71: =R45*R72 -> 15088.409 | S71: =S45*S72 -> 15842.829
B72: % of revenue | F72: =F33 -> 0.044308436 | G72: =G33 -> 0.041051225 | H72: =H33 -> 0.048225418 | I72: =I33 -> 0.040274666 | J72: =J33 -> 0.030846024 | K72: =K33 -> 0.028159299 | L72: =L33 -> 0.030053355 | M72: =OFFSET(M72,$D$9,0) -> 0.029686226 | N72: =OFFSET(N72,$D$9,0) -> 0.029299626 | O72: =OFFSET(O72,$D$9,0) -> 0.029299626 | P72: =OFFSET(P72,$D$9,0) -> 0.029299626 | Q72: =OFFSET(Q72,$D$9,0) -> 0.029299626 | R72: =OFFSET(R72,$D$9,0) -> 0.029299626 | S72: =OFFSET(S72,$D$9,0) -> 0.029299626
B73: Conservative case | M73: =I10 -> 0.024686226 | N73: =M73 -> 0.024686226 | O73: =N73 -> 0.024686226 | P73: =O73 -> 0.024686226 | Q73: =P73 -> 0.024686226 | R73: =Q73 -> 0.024686226 | S73: =R73 -> 0.024686226
B74: Base case | M74: =M33 -> 0.029686226 | N74: =N33 -> 0.029299626 | O74: =N74 -> 0.029299626 | P74: =O74 -> 0.029299626 | Q74: =P74 -> 0.029299626 | R74: =Q74 -> 0.029299626 | S74: =R74 -> 0.029299626
B75: Optimistic case | M75: =M10 -> 0.034686226 | N75: =M75 -> 0.034686226 | O75: =N75 -> 0.034686226 | P75: =O75 -> 0.034686226 | Q75: =P75 -> 0.034686226 | R75: =Q75 -> 0.034686226 | S75: =R75 -> 0.034686226
B77: CapEx | F77: =F36 -> 12795 | G77: =G36 -> 13313 | H77: =H36 -> 10495 | I77: =I36 -> 7309 | J77: =J36 -> 11085 | K77: =K36 -> 10708 | L77: =L36 -> 10959 | M77: =M45*M78 -> 11200.209 | N77: =N45*N78 -> 19999.14 | O77: =O45*O78 -> 25815.923 | P77: =P45*P78 -> 32156.962 | Q77: =Q45*Q78 -> 39008.129 | R77: =R45*R78 -> 46347.239 | S77: =S45*S78 -> 48664.601
B78: % of revenue | F78: =F37 -> 0.055816327 | G78: =G37 -> 0.050125191 | H78: =H37 -> 0.040338389 | I78: =I37 -> 0.026625139 | J78: =J37 -> 0.030302036 | K78: =K37 -> 0.027155059 | L78: =L37 -> 0.028592301 | M78: =OFFSET(M78,$D$10,0) -> 0.028683132 | N78: =OFFSET(N78,$D$10,0) -> 0.048143497 | O78: =OFFSET(O78,$D$10,0) -> 0.058607623 | P78: =OFFSET(P78,$D$10,0) -> 0.069071749 | Q78: =OFFSET(Q78,$D$10,0) -> 0.079535874 | R78: =OFFSET(R78,$D$10,0) -> 0.09 | S78: =OFFSET(S78,$D$10,0) -> 0.09
B79: Conservative case | M79: =M80 -> 0.028683132 | N79: =N80+2% -> 0.048143497 | O79: =N79-(($N$79-$S$79)/($S$43-$O$43)) -> 0.058607623 | P79: =O79-(($N$79-$S$79)/($S$43-$O$43)) -> 0.069071749 | Q79: =P79-(($N$79-$S$79)/($S$43-$O$43)) -> 0.079535874 | R79: =Q79-(($N$79-$S$79)/($S$43-$O$43)) -> 0.09 | S79: =I11 -> 0.09
B80: Base case | M80: =M37 -> 0.028683132 | N80: =N37 -> 0.028143497 | O80: =N80-(($N$80-$S$80)/($S$43-$O$43)) -> 0.038607623 | P80: =O80-(($N$79-$S$79)/($S$43-$O$43)) -> 0.049071749 | Q80: =P80-(($N$79-$S$79)/($S$43-$O$43)) -> 0.059535874 | R80: =Q80-(($N$79-$S$79)/($S$43-$O$43)) -> 0.07 | S80: =K11 -> 0.07
B81: Optimistic case | M81: =M80 -> 0.028683132 | N81: =N80-2% -> 0.0081434971 | O81: =N81-(($N$81-$S$81)/($S$43-$O$43)) -> 0.018607623 | P81: =O81-(($N$81-$S$81)/($S$43-$O$43)) -> 0.029071749 | Q81: =P81-(($N$81-$S$81)/($S$43-$O$43)) -> 0.039535874 | R81: =Q81-(($N$81-$S$81)/($S$43-$O$43)) -> 0.05 | S81: =M11 -> 0.05
B83: Change in NWC | F83: =F39 -> -4923 | G83: =G39 -> 34694 | H83: =H39 -> -3488 | I83: =I39 -> 5690 | J83: =J39 -> -4911 | K83: =K39 -> 1200 | L83: =L39 -> -6577 | M83: =M45*M84 -> -3584.7623 | N83: =N45*N84 -> -3225.8817 | O83: =O45*O84 -> -5007.6866 | P83: =P45*P84 -> -4394.0201 | Q83: =Q45*Q84 -> -4671.061 | R83: =R45*R84 -> -5206.4709 | S83: =S45*S84 -> -5240.0073
B84: % of revenue | F84: =F40 -> -0.021475872 | G84: =G40 -> 0.13062746 | H84: =H40 -> -0.013406413 | I84: =I40 -> 0.020727465 | J84: =J40 -> -0.013424745 | K84: =K40 -> 0.0030431519 | L84: =L40 -> -0.017159555 | M84: =AVERAGE(J84:L84) -> -0.0091803827 | N84: =AVERAGE(K84:M84) -> -0.0077655952 | O84: =AVERAGE(L84:N84) -> -0.011368511 | P84: =AVERAGE(M84:O84) -> -0.009438163 | Q84: =AVERAGE(N84:P84) -> -0.0095240897 | R84: =AVERAGE(O84:Q84) -> -0.010110255 | S84: =AVERAGE(P84:R84) -> -0.0096908357
B85: Conservative case | M85: =M$84*M50 -> -3549.5753 | N85: =N$84*N50 -> -3164.1918 | O85: =O$84*O50 -> -4865.6001 | P85: =P$84*P50 -> -4228.9512 | Q85: =Q$84*Q50 -> -4452.9101 | R85: =R$84*R50 -> -4916.0453 | S85: =S$84*S50 -> -4900.5899
B86: Base case | M86: =M$84*M51 -> -3584.7623 | N86: =N$84*N51 -> -3225.8817 | O86: =O$84*O51 -> -5007.6866 | P86: =P$84*P51 -> -4394.0201 | Q86: =Q$84*Q51 -> -4671.061 | R86: =R$84*R51 -> -5206.4709 | S86: =S$84*S51 -> -5240.0073
B87: Optimistic case | M87: =M$84*M52 -> -3619.9493 | N87: =N$84*N52 -> -3288.1669 | O87: =O$84*O52 -> -5152.5122 | P87: =P$84*P52 -> -4563.8743 | Q87: =Q$84*Q52 -> -4897.6786 | R87: =R$84*R52 -> -5511.0552 | S87: =S$84*S52 -> -5599.3778
B89: Unlevered Free Cash Flow | M89: =M66+M71-M77-M83 -> 115516.74 | N89: =N66+N71-N77-N83 -> 113418.72 | O89: =O66+O71-O77-O83 -> 117244.21 | P89: =P66+P71-P77-P83 -> 118147.08 | Q89: =Q66+Q71-Q77-Q83 -> 119373.1 | R89: =R66+R71-R77-R83 -> 120254.91 | S89: =S66+S71-S77-S83 -> 126040.87
B90: Conservative case | M90: =M67+(M73*M50)-(M79*M50)-M$85 -> 109152.02 | N90: =N67+(N73*N50)-(N79*N50)-N$85 -> 105913.59 | O90: =O67+(O73*O50)-(O79*O50)-O$85 -> 104780.01 | P90: =P67+(P73*P50)-(P79*P50)-P$85 -> 104142.42 | Q90: =Q67+(Q73*Q50)-(Q79*Q50)-Q$85 -> 103816.07 | R90: =R67+(R73*R50)-(R79*R50)-R$85 -> 103165.61 | S90: =S67+(S73*S50)-(S79*S50)-S$85 -> 107080.14
B91: Base case | M91: =M68+(M74*M51)-(M80*M51)-M$86 -> 115516.74 | N91: =N68+(N74*N51)-(N80*N51)-N$86 -> 121726.86 | O91: =O68+(O74*O51)-(O80*O51)-O$86 -> 126053.96 | P91: =P68+(P74*P51)-(P80*P51)-P$86 -> 127458.25 | Q91: =Q68+(Q74*Q51)-(Q80*Q51)-Q$86 -> 129182.04 | R91: =R68+(R74*R51)-(R80*R51)-R$86 -> 130554.3 | S91: =S68+(S74*S51)-(S80*S51)-S$86 -> 136855.23
B92: Optimistic case | M92: =M69+(M75*M52)-(M81*M52)-M$87 -> 121985.16 | N92: =N69+(N75*N52)-(N81*N52)-N$87 -> 138418.36 | O92: =O69+(O75*O52)-(O81*O52)-O$87 -> 150458.67 | P92: =P69+(P75*P52)-(P81*P52)-P$87 -> 154533.55 | Q92: =Q69+(Q75*Q52)-(Q81*Q52)-Q$87 -> 159003.14 | R92: =R69+(R75*R52)-(R81*R52)-R$87 -> 163158.9 | S92: =S69+(S75*S52)-(S81*S52)-S$87 -> 172706.09
M94: 1 | N94: 2 | O94: 3 | P94: 4 | Q94: 5 | R94: 6 | S94: 7
B95: Present value of FCF | M95: =M89/(1+$D$16)^M$94 -> 105937.89 | N95: =N89/(1+$D$16)^N$94 -> 95388.838 | O95: =O89/(1+$D$16)^O$94 -> 90429.6 | P95: =P89/(1+$D$16)^P$94 -> 83569.651 | Q95: =Q89/(1+$D$16)^Q$94 -> 77435.213 | R95: =R89/(1+$D$16)^R$94 -> 71538.732 | S95: =S89/(1+$D$16)^S$94 -> 68763.221
B96: Conservative case | M96: =M90/(1+$I$12)^M$94 -> 99191.281 | N96: =N90/(1+$I$12)^N$94 -> 87465.173 | O96: =O90/(1+$I$12)^O$94 -> 78632.779 | P96: =P90/(1+$I$12)^P$94 -> 71022.278 | Q96: =Q90/(1+$I$12)^Q$94 -> 64338.842 | R96: =R90/(1+$I$12)^R$94 -> 58101.236 | S96: =S90/(1+$I$12)^S$94 -> 54802.589
B97: Base case | M97: =M91/(1+$K$12)^M$94 -> 105937.89 | N97: =N91/(1+$K$12)^N$94 -> 102376.25 | O97: =O91/(1+$K$12)^O$94 -> 97224.495 | P97: =P91/(1+$K$12)^P$94 -> 90155.78 | Q97: =Q91/(1+$K$12)^Q$94 -> 83798.098 | R97: =R91/(1+$K$12)^R$94 -> 77665.759 | S97: =S91/(1+$K$12)^S$94 -> 74663.132
B98: Optimistic case | M98: =M92/(1+$M$12)^M$94 -> 112905.37 | N98: =N92/(1+$M$12)^N$94 -> 118579.3 | O98: =O92/(1+$M$12)^O$94 -> 119299.88 | P98: =P92/(1+$M$12)^P$94 -> 113410.47 | Q98: =Q92/(1+$M$12)^Q$94 -> 108004.96 | R98: =R92/(1+$M$12)^R$94 -> 102578.5 | S98: =S92/(1+$M$12)^S$94 -> 100498.79

Sheet RATIOS
B2: Ticker | C2: AAPL
B4: Profitability analysis | F4: 2023 | H4: TTM | J4: Com services | L4: Technology
B5: Gross Profit margin | F5: {=_xldudf_WISE($C$2,"Gross Profit Ratio",$F$4)} -> 0.4413113 | H5: {=_xldudf_WISE($C$2,"Gross Profit Ratio",$H$4)} -> 0.47862405 | J5: 0.5029 | L5: 0.4716
B6: Net Income margin | F6: {=_xldudf_WISE($C$2,"Net Income Ratio",$F$4)} -> 0.25306234 | H6: {=_xldudf_WISE($C$2,"Net Income Ratio",$H$4)} -> 0.27151882 | J6: -0.0252 | L6: -0.0321
B7: ROA | F7: {=_xldudf_WISE($C$2,"Return On Tangible Assets",$F$4)} -> 0.27509835 | H7: {=_xldudf_WISE($C$2,"Return On Tangible Assets",$H$4)} -> 0.35046662 | J7: -0.0345 | L7: -0.0178
B8: ROE | F8: {=_xldudf_WISE($C$2,"ROE",$F$4)} -> 1.5607601 | H8: {=_xldudf_WISE($C$2,"ROE",$H$4)} -> 1.4668924 | J8: -0.0203 | L8: -0.0155
B9: ROIC | F9: {=_xldudf_WISE($C$2,"ROIC",$F$4)} -> 0.43389183 | H9: {=_xldudf_WISE($C$2,"ROIC",$H$4)} -> 0.49573922 | J9: -0.0198 | L9: -0.0094
B11: Market Value analysis | F11: 2023 | H11: TTM | J11: Com services | L11: Technology
B12: PE ratio | F12: {=_xldudf_WISE($C$2,$B12,F$11)} -> 27.790812 | H12: {=_xldudf_WISE($C$2,$B12,H$11)} -> 39.505428 | J12: 12.09 | L12: 22.79
B13: PB ratio | F13: {=_xldudf_WISE($C$2,$B13,F$11)} -> 43.374791 | H13: {=_xldudf_WISE($C$2,$B13,H$11)} -> 45.241008 | J13: 1.42 | L13: 2.53
B14: Price To Sales Ratio | F14: {=_xldudf_WISE($C$2,$B14,F$11)} -> 7.0328079 | H14: {=_xldudf_WISE($C$2,$B14,H$11)} -> 10.654988 | J14: 1.13 | L14: 2.38
B15: Enterprise Value Over EBITDA | F15: {=_xldudf_WISE($C$2,$B15,F$11)} -> 21.592832 | H15: {=_xldudf_WISE($C$2,$B15,H$11)} -> 30.302697 | J15: 4.11 | L15: 4.45
B16: Ev To Sales | F16: {=_xldudf_WISE($C$2,$B16,F$11)} -> 7.2779649 | H16: {=_xldudf_WISE($C$2,$B16,H$11)} -> 10.762162 | J16: 1.55 | L16: 2.27
B18: Liquidity analysis | F18: 2023 | H18: TTM | J18: Com services | L18: Technology
B19: Current ratio | F19: {=_xldudf_WISE($C$2,B19,$F$18)} -> 0.98801167 | H19: {=_xldudf_WISE($C$2,B19,$H$18)} -> 1.0703575 | J19: 1.55 | L19: 2.26
B21: Financial Leverage analysis | F21: 2023 | H21: TTM | J21: Com services | L21: Technology
B22: Debt-to-equity | F22: {=_xldudf_WISE($C$2,"Debt to equity",$F21)} -> 1.994175 | H22: {=_xldudf_WISE($C$2,"Debt to equity",$H21)} -> 0.79547567 | J22: 0.56 | L22: 0.26
B23: Interest Coverage | F23: {=_xldudf_WISE($C$2,B23,$F$21)} -> 29.062039 | H23: {=_xldudf_WISE($C$2,B23,$H$21)} -> 0 | J23: 2.71 | L23: 16.09
B24: Days Sales Outstanding | F24: {=_xldudf_WISE($C$2,B24,$F$21)} -> 58.075649 | H24: {=_xldudf_WISE($C$2,B24,$H$21)} -> 43.264727 | J24: 45.52 | L24: 54.98
B25: Days Payables Outstanding | F25: {=_xldudf_WISE($C$2,B25,$F$21)} -> 106.72147 | H25: {=_xldudf_WISE($C$2,B25,$H$21)} -> 88.933577 | J25: 48.68 | L25: 50.22
B26: Days Of Inventory On Hand | F26: {=_xldudf_WISE($C$2,B26,$F$21)} -> 10.791292 | H26: {=_xldudf_WISE($C$2,B26,$H$21)} -> 10.462865 | J26: 24.83 | L26: 84.73

Sheet Data
B2: =INFO!E2 -> AAPL
B3: close
B5: {=_xldudf_WISEPRICE(B2,B3,365*7)} -> 2026-07-16 | C5: 327.5
B6: 2026-07-15 | C6: 327.5
B7: 2026-07-14 | C7: 314.86
B8: 2026-07-13 | C8: 317.31
B9: 2026-07-10 | C9: 315.32
B10: 2026-07-09 | C10: 316.22
B11: 2026-07-08 | C11: 313.39
B12: 2026-07-07 | C12: 310.66
B13: 2026-07-06 | C13: 312.66
B14: 2026-07-02 | C14: 308.63
B15: 2026-07-01 | C15: 294.38
B16: 2026-06-30 | C16: 289.36
B17: 2026-06-29 | C17: 281.74
... B1761: 2019-07-19 | C1761: 50.65

Sheet AAPL - Income Statement FY
A1: Income Statement
A2: Company | B2: AAPL (NASDAQ)
A3: Currency | B3: USD
A4: Period | B4: FY
A5: Date | B5: 45927 | C5: 45563 | D5: 45199 | E5: 44828 | F5: 44464 | G5: 44100 | H5: 43736 | I5: 43372 | J5: 43008 | K5: 42637 | L5: 42273 | M5: 41909 | N5: 41545 | O5: 41181 | P5: 40810 | Q5: 40446 | R5: 40082 | S5: 39718 | T5: 39354
A7: Revenue | B7: 416161000000 | C7: 391035000000 | D7: 383285000000 | E7: 394328000000 | F7: 365817000000 | G7: 274515000000 | H7: 260174000000 | I7: 265595000000 | J7: 229234000000 | K7: 215639000000 | L7: 233715000000 | M7: 182795000000 | N7: 170910000000 | O7: 156508000000 | P7: 108249000000 | Q7: 65225000000 | R7: 42603000000 | S7: 32479000000 | T7: 24006000000
A9: Cost Of Revenue | B9: 220960000000 | C9: 210352000000 | D9: 214137000000 | E9: 223546000000 | F9: 212981000000 | G9: 169559000000 | H9: 161782000000 | I9: 163756000000 | J9: 141048000000 | K9: 131376000000 | L9: 140089000000 | M9: 112258000000 | N9: 106606000000 | O9: 87846000000 | P9: 64431000000 | Q9: 39541000000 | R9: 25751000000 | S9: 21334000000 | T9: 15852000000
A10: Gross Profit | B10: 195201000000 | C10: 180683000000 | D10: 169148000000 | E10: 170782000000 | F10: 152836000000 | G10: 104956000000 | H10: 98392000000 | I10: 101839000000 | J10: 88186000000 | K10: 84263000000 | L10: 93626000000 | M10: 70537000000 | N10: 64304000000 | O10: 68662000000 | P10: 43818000000 | Q10: 25684000000 | R10: 16852000000 | S10: 11145000000 | T10: 8154000000
A11: Gross Profit Ratio | B11: 0.46905164 | C11: 0.4620635 | D11: 0.4413113 | E11: 0.43309631 | F11: 0.4177936 | G11: 0.38233248 | H11: 0.37817768 | I11: 0.38343719 | J11: 0.3846986 | K11: 0.39075956 | L11: 0.40059902 | M11: 0.38588036 | N11: 0.37624481 | O11: 0.4387124 | P11: 0.40478896 | Q11: 0.39377539 | R11: 0.395559 | S11: 0.3431448 | T11: 0.33966508
A13: Research And Development Expenses | B13: 34550000000 | C13: 31370000000 | D13: 29915000000 | E13: 26251000000 | F13: 21914000000 | G13: 18752000000 | H13: 16217000000 | I13: 14236000000 | J13: 11581000000 | K13: 10045000000 | L13: 8067000000 | M13: 6041000000 | N13: 4475000000 | O13: 3381000000 | P13: 2429000000 | Q13: 1782000000 | R13: 1333000000 | S13: 1109000000 | T13: 782000000
A14: Selling General And Administrative Expenses | B14: 27601000000 | C14: 26097000000 | D14: 24932000000 | E14: 25094000000 | F14: 21973000000 | G14: 19916000000 | H14: 18245000000 | I14: 16705000000 | J14: 15261000000 | K14: 14194000000 | L14: 14329000000 | M14: 11993000000 | N14: 10830000000 | O14: 10040000000 | P14: 7599000000 | Q14: 5517000000 | R14: 4149000000 | S14: 3761000000 | T14: 2963000000
A15: General And Administrative Expenses | B15: 27601000000 | C15: 7458000000 | D15: 0 | E15: 0 | F15: 0 | G15: 0 | H15: 0 | I15: 0 | J15: 0 | K15: 0 | L15: 0 | M15: 0 | N15: 9730000000 | O15: 9040000000 | P15: 0 | Q15: 0 | R15: 0 | S15: 0 | T15: 0
A16: Selling And Marketing Expenses | B16: 0 | C16: 18639000000 | D16: 0 | E16: 0 | F16: 0 | G16: 0 | H16: 0 | I16: 0 | J16: 0 | K16: 0 | L16: 0 | M16: 0 | N16: 1100000000 | O16: 1000000000 | P16: 0 | Q16: 0 | R16: 0 | S16: 0 | T16: 0
A17: Other Expenses | B17: 0 | C17: 0 | D17: 0 | E17: 0 | F17: 0 | G17: 0 | H17: 0 | I17: 0 | J17: 0 | K17: 0 | L17: 0 | M17: 0 | N17: 0 | O17: 0 | P17: 0 | Q17: 0 | R17: 0 | S17: 0 | T17: 0
A18: Operating Expenses | B18: 62151000000 | C18: 57467000000 | D18: 54847000000 | E18: 51345000000 | F18: 43887000000 | G18: 38668000000 | H18: 34462000000 | I18: 30941000000 | J18: 26842000000 | K18: 24239000000 | L18: 22396000000 | M18: 18034000000 | N18: 15305000000 | O18: 13421000000 | P18: 10028000000 | Q18: 7299000000 | R18: 5482000000 | S18: 4870000000 | T18: 3745000000
A20: Cost And Expenses | B20: 283111000000 | C20: 267819000000 | D20: 268984000000 | E20: 274891000000 | F20: 256868000000 | G20: 208227000000 | H20: 196244000000 | I20: 194697000000 | J20: 167890000000 | K20: 155615000000 | L20: 162485000000 | M20: 130292000000 | N20: 121911000000 | O20: 101267000000 | P20: 74459000000 | Q20: 46840000000 | R20: 31233000000 | S20: 26204000000 | T20: 19597000000
... A38: Weighted Average Shs Out Dil | B38: 15004697000 | C38: 15408095000 | D38: 15812547000 | E38: 16325819000 | F38: 16864919000 | G38: 17528214000 | H38: 18595652000 | I38: 20000436000 | J38: 21006768000 | K38: 22001124000 | L38: 23172276000 | M38: 24490652000 | N38: 26086536000 | O38: 26469932000 | P38: 26226060000 | Q38: 25891961891 | R38: 25396165396 | S38: 25259892000 | T38: 24900176000

Sheet AAPL - Balance Sheet FY
A1: Balance Sheet
A2: Company | B2: AAPL (NASDAQ)
A3: Currency | B3: ='AAPL - Income Statement FY'!B3 -> USD
A4: Period | B4: FY
A5: Date | B5: 45927 | C5: 45563 | D5: 45199 | E5: 44828 | F5: 44464 | G5: 44100 | H5: 43736 | I5: 43372 | J5: 43008 | K5: 42637 | L5: 42273 | M5: 41909 | N5: 41545 | O5: 41181 | P5: 40810 | Q5: 40446 | R5: 40082 | S5: 39718 | T5: 39354
A7: Cash And Cash Equivalents | B7: 35934000000 | C7: 29943000000 | D7: 29965000000 | E7: 23646000000 | F7: 34940000000 | G7: 38016000000 | H7: 48844000000 | I7: 25913000000 | J7: 20289000000 | K7: 20484000000 | L7: 21120000000 | M7: 13844000000 | N7: 14259000000 | O7: 10746000000 | P7: 9815000000 | Q7: 11261000000 | R7: 5263000000 | S7: 11875000000 | T7: 9352000000
A8: Short Term Investments | B8: 18763000000 | C8: 35228000000 | D8: 31590000000 | E8: 24658000000 | F8: 27699000000 | G8: 52927000000 | H8: 51713000000 | I8: 40388000000 | J8: 53892000000 | K8: 46671000000 | L8: 20481000000 | M8: 11233000000 | N8: 26287000000 | O8: 18383000000 | P8: 16137000000 | Q8: 14359000000 | R8: 18201000000 | S8: 10236000000 | T8: 6034000000
A9: Cash And Short Term Investments | B9: 54697000000 | C9: 65171000000 | D9: 61555000000 | E9: 48304000000 | F9: 62639000000 | G9: 90943000000 | H9: 100557000000 | I9: 66301000000 | J9: 74181000000 | K9: 67155000000 | L9: 41601000000 | M9: 25077000000 | N9: 40546000000 | O9: 29129000000 | P9: 25952000000 | Q9: 25620000000 | R9: 23464000000 | S9: 22111000000 | T9: 15386000000
A10: Net Receivables | B10: 72957000000 | C10: 66243000000 | D10: 60985000000 | E10: 60932000000 | F10: 51506000000 | G10: 37445000000 | H10: 45804000000 | I10: 48995000000 | J10: 35673000000 | K10: 29299000000 | L10: 30343000000 | M10: 27219000000 | N10: 20641000000 | O10: 18692000000 | P10: 11717000000 | Q10: 9924000000 | R10: 5057000000 | S10: 4704000000 | T10: 4029000000
A11: Inventory | B11: 5718000000 | C11: 7286000000 | D11: 6331000000 | E11: 4946000000 | F11: 6580000000 | G11: 4061000000 | H11: 4106000000 | I11: 3956000000 | J11: 4855000000 | K11: 2132000000 | L11: 2349000000 | M11: 2111000000 | N11: 1764000000 | O11: 791000000 | P11: 776000000 | Q11: 1051000000 | R11: 455000000 | S11: 509000000 | T11: 346000000
A12: Other Current Assets | B12: 14585000000 | C12: 14287000000 | D12: 14695000000 | E12: 21223000000 | F12: 14111000000 | G12: 11264000000 | H12: 12352000000 | I12: 12087000000 | J12: 13936000000 | K12: 8283000000 | L12: 15085000000 | M12: 14124000000 | N12: 10335000000 | O12: 9041000000 | P12: 6543000000 | Q12: 5083000000 | R12: 2579000000 | S12: 2682000000 | T12: 2195000000
A13: Total Current Assets | B13: 147957000000 | C13: 152987000000 | D13: 143566000000 | E13: 135405000000 | F13: 134836000000 | G13: 143713000000 | H13: 162819000000 | I13: 131339000000 | J13: 128645000000 | K13: 106869000000 | L13: 89378000000 | M13: 68531000000 | N13: 73286000000 | O13: 57653000000 | P13: 44988000000 | Q13: 41678000000 | R13: 31555000000 | S13: 30006000000 | T13: 21956000000
A15: Property Plant Equipment Net | B15: 49834000000 | C15: 45680000000 | D15: 54376000000 | E15: 52534000000 | F15: 49527000000 | G15: 45336000000 | H15: 37378000000 | I15: 41304000000 | J15: 33783000000 | K15: 27010000000 | L15: 22471000000 | M15: 20624000000 | N15: 16597000000 | O15: 15452000000 | P15: 7777000000 | Q15: 4768000000 | R15: 2954000000 | S15: 2455000000 | T15: 1832000000
A16: Goodwill | B16: 0 | C16: 0 | D16: 0 | E16: 0 | F16: 0 | G16: 0 | H16: 0 | I16: 0 | J16: 5717000000 | K16: 5414000000 | L16: 5116000000 | M16: 4616000000 | N16: 1577000000 | O16: 1135000000 | P16: 896000000 | Q16: 741000000 | R16: 206000000 | S16: 207000000 | T16: 38000000
A17: Intangible Assets | B17: 0 | C17: 0 | D17: 0 | E17: 0 | F17: 0 | G17: 0 | H17: 0 | I17: 0 | J17: 2298000000 | K17: 3206000000 | L17: 3893000000 | M17: 4142000000 | N17: 4179000000 | O17: 4224000000 | P17: 3536000000 | Q17: 342000000 | R17: 247000000 | S17: 285000000 | T17: 299000000
A18: Goodwill And Intangible Assets | B18: 0 | C18: 0 | D18: 0 | E18: 0 | F18: 0 | G18: 0 | H18: 0 | I18: 0 | J18: 8015000000 | K18: 8620000000 | L18: 9009000000 | M18: 8758000000 | N18: 5756000000 | O18: 5359000000 | P18: 4432000000 | Q18: 1083000000 | R18: 453000000 | S18: 492000000 | T18: 337000000
... A52: Net Debt | B52: 76443000000 | C52: 89116000000 | D52: 93965000000 | E52: 108834000000 | F52: 101582000000 | G52: 84262000000 | H52: 59203000000 | I52: 88570000000 | J52: 95391000000 | K52: 66548000000 | L52: 43208000000 | M52: 21451000000 | N52: 2701000000 | O52: -10746000000 | P52: -9815000000 | Q52: -11261000000 | R52: -5263000000 | S52: -11875000000 | T52: -9352000000

Sheet AAPL - Cash Flow FY
A1: Cash Flow
A2: Company | B2: AAPL (NASDAQ)
A3: Currency | B3: ='AAPL - Income Statement FY'!B3 -> USD
A4: Period | B4: FY
A5: Date | B5: 45927 | C5: 45563 | D5: 45199 | E5: 44828 | F5: 44464 | G5: 44100 | H5: 43736 | I5: 43372 | J5: 43008 | K5: 42637 | L5: 42273 | M5: 41909 | N5: 41545 | O5: 41181 | P5: 40810 | Q5: 40446 | R5: 40082 | S5: 39718 | T5: 39354
A7: Net Income | B7: 112010000000 | C7: 93736000000 | D7: 96995000000 | E7: 99803000000 | F7: 94680000000 | G7: 57411000000 | H7: 55256000000 | I7: 59531000000 | J7: 48351000000 | K7: 45687000000 | L7: 53394000000 | M7: 39510000000 | N7: 37037000000 | O7: 41733000000 | P7: 25922000000 | Q7: 14013000000 | R7: 8235000000 | S7: 6119000000 | T7: 3496000000
A8: Depreciation And Amortization | B8: 11698000000 | C8: 11445000000 | D8: 11519000000 | E8: 11104000000 | F8: 11284000000 | G8: 11056000000 | H8: 12547000000 | I8: 10903000000 | J8: 10157000000 | K8: 10505000000 | L8: 11257000000 | M8: 7946000000 | N8: 6757000000 | O8: 3277000000 | P8: 1814000000 | Q8: 1027000000 | R8: 734000000 | S8: 496000000 | T8: 317000000
A9: Deferred Income Tax | B9: 0 | C9: 0 | D9: 0 | E9: 895000000 | F9: -4774000000 | G9: -215000000 | H9: -340000000 | I9: -32590000000 | J9: 5966000000 | K9: 4938000000 | L9: 1382000000 | M9: 2347000000 | N9: 1141000000 | O9: 4405000000 | P9: 2868000000 | Q9: 1440000000 | R9: 1040000000 | S9: 398000000 | T9: 78000000
A10: Stock Based Compensation | B10: 12863000000 | C10: 11688000000 | D10: 10833000000 | E10: 9038000000 | F10: 7906000000 | G10: 6829000000 | H10: 6068000000 | I10: 5340000000 | J10: 4840000000 | K10: 4210000000 | L10: 3586000000 | M10: 2863000000 | N10: 2253000000 | O10: 1740000000 | P10: 1168000000 | Q10: 879000000 | R10: 710000000 | S10: 516000000 | T10: 242000000
A11: Change In Working Capital | B11: -25000000000 | C11: 3651000000 | D11: -6577000000 | E11: 1200000000 | F11: -4911000000 | G11: 5690000000 | H11: -3488000000 | I11: 34694000000 | J11: -4923000000 | K11: 405000000 | L11: 11262000000 | M11: 7047000000 | N11: 6478000000 | O11: -299000000 | P11: 5757000000 | Q11: 1236000000 | R11: -586000000 | S11: 2045000000 | T11: 1325000000
A12: Accounts Receivables | B12: -7029000000 | C12: -5144000000 | D12: -417000000 | E12: -9343000000 | F12: -14028000000 | G12: 8470000000 | H12: 3176000000 | I12: -13332000000 | J12: -6347000000 | K12: 476000000 | L12: -3318000000 | M12: -6452000000 | N12: -1949000000 | O12: -6965000000 | P12: -1791000000 | Q12: -4860000000 | R12: -353000000 | S12: -675000000 | T12: -385000000
A13: Inventory | B13: 1400000000 | C13: -1046000000 | D13: -1618000000 | E13: 1484000000 | F13: -2642000000 | G13: -127000000 | H13: -289000000 | I13: 828000000 | J13: -2723000000 | K13: 217000000 | L13: -238000000 | M13: -76000000 | N13: -973000000 | O13: -15000000 | P13: 275000000 | Q13: -596000000 | R13: 54000000 | S13: -163000000 | T13: -76000000
A14: Accounts Payables | B14: 902000000 | C14: 6020000000 | D14: -1889000000 | E14: 9448000000 | F14: 12326000000 | G14: -4062000000 | H14: -1923000000 | I14: 9175000000 | J14: 8966000000 | K14: 2117000000 | L14: 5001000000 | M14: 5938000000 | N14: 2340000000 | O14: 4467000000 | P14: 2515000000 | Q14: 6307000000 | R14: 92000000 | S14: 596000000 | T14: 1494000000
A15: Other Working Capital | B15: -20273000000 | C15: 3821000000 | D15: -2653000000 | E15: -389000000 | F15: -567000000 | G15: 1409000000 | H15: -4452000000 | I15: 38023000000 | J15: -4819000000 | K15: -2405000000 | L15: 9817000000 | M15: 7637000000 | N15: 7060000000 | O15: 2214000000 | P15: 4758000000 | Q15: 385000000 | R15: -379000000 | S15: 2287000000 | T15: 292000000
A16: Other Non Cash Items | B16: -89000000 | C16: -2266000000 | D16: -2227000000 | E16: 111000000 | F16: -147000000 | G16: -97000000 | H16: -652000000 | I16: -444000000 | J16: -166000000 | K16: 486000000 | L16: 385000000 | M16: 0 | N16: 0 | O16: 0 | P16: 0 | Q16: 0 | R16: 26000000 | S16: 22000000 | T16: 12000000
A17: Net Cash Provided By Operating Activities | B17: 111482000000 | C17: 118254000000 | D17: 110543000000 | E17: 122151000000 | F17: 104038000000 | G17: 80674000000 | H17: 69391000000 | I17: 77434000000 | J17: 64225000000 | K17: 66231000000 | L17: 81266000000 | M17: 59713000000 | N17: 53666000000 | O17: 50856000000 | P17: 37529000000 | Q17: 18595000000 | R17: 10159000000 | S17: 9596000000 | T17: 5470000000
... A39: Free Cash Flow | B39: 98767000000 | C39: 108807000000 | D39: 99584000000 | E39: 111443000000 | F39: 92953000000 | G39: 73365000000 | H39: 58896000000 | I39: 64121000000 | J39: 51430000000 | K39: 52683000000 | L39: 69778000000 | M39: 49900000000 | N39: 44590000000 | O39: 41454000000 | P39: 30077000000 | Q39: 16474000000 | R39: 8946000000 | S39: 8397000000 | T39: 4484000000

Sheet AAPL - Key Metrics FY
A1: Key Metrics
A2: Company | B2: AAPL (NASDAQ)
A3: Currency | B3: ='AAPL - Income Statement FY'!B3 -> USD
A4: Period | B4: FY
A5: Date | B5: 45927 | C5: 45563 | D5: 45199 | E5: 44828 | F5: 44464 | G5: 44100 | H5: 43736 | I5: 43372 | J5: 43008 | K5: 42637 | L5: 42273 | M5: 41909 | N5: 41545 | O5: 41181 | P5: 40810 | Q5: 40446 | R5: 40082 | S5: 39718 | T5: 39354
A6: Revenue Per Share | B6: 27.839649 | C6: 25.484915 | D6: 24.344473 | E6: 24.317273 | F6: 21.903541 | G6: 15.820258 | H6: 14.085283 | I6: 13.399334 | J6: 10.984444 | K6: 9.854053 | L6: 10.15548 | M6: 7.5093598 | N6: 6.5964812 | O6: 5.9793092 | P6: 4.1828492 | Q6: 2.5613654 | R6: 1.7038152 | S6: 1.3157609 | T6: 0.99162762
A7: Net Income Per Share | B7: 7.4930595 | C7: 6.1090541 | D7: 6.1606693 | E7: 6.1546144 | F7: 5.6690293 | G7: 3.3085873 | H7: 2.9914458 | I7: 3.0033537 | J7: 2.3168851 | K7: 2.0877583 | L7: 2.3200979 | M7: 1.6231013 | N7: 1.4294885 | O7: 1.5943882 | P7: 1.0016519 | Q7: 0.55028614 | R7: 0.32934107 | S7: 0.19583079 | T7: 0.14436968
A8: Operating Cash Flow Per Share | B8: 7.4577382 | C8: 7.7069651 | D8: 7.0211749 | E8: 7.5327626 | F8: 6.2293459 | G8: 4.6492304 | H8: 3.7566855 | I8: 3.9065645 | J8: 3.077536 | K8: 3.0265573 | L8: 3.5312034 | M8: 2.4530562 | N8: 2.0713051 | O8: 1.9429278 | P8: 1.450158 | Q8: 0.73021985 | R8: 0.40628731 | S8: 0.38874478 | T8: 0.22595197
A9: Free Cash Flow Per Share | B9: 6.6071512 | C9: 7.091276 | D9: 6.3251104 | E9: 6.8724256 | F9: 5.565624 | G9: 4.2280139 | H9: 3.1885079 | I9: 3.2349204 | J9: 2.4644247 | K9: 2.4074545 | L9: 3.0320222 | M9: 2.0499306 | N9: 1.7210058 | O9: 1.5837292 | P9: 1.1622052 | Q9: 0.64692885 | R9: 0.35777599 | S9: 0.34017194 | T9: 0.18522279
A10: Cash Per Share | B10: 3.6590293 | C10: 4.247388 | D10: 3.909686 | E10: 2.9787932 | F10: 3.7505527 | G10: 5.2410314 | H10: 5.4439484 | I10: 3.3449019 | J10: 3.554608 | K10: 3.0687813 | L10: 1.8076636 | M10: 1.0301825 | N10: 1.5649226 | O10: 1.1128587 | P10: 1.0028111 | Q10: 1.0060894 | R10: 0.9383921 | S10: 0.89574154 | T10: 0.63555705
A11: Book Value Per Share | B11: 4.9324681 | C11: 3.711601 | D11: 3.9472236 | E11: 3.1248221 | F11: 3.7775566 | G11: 3.7654767 | H11: 4.8988335 | I11: 5.4055928 | J11: 6.4232692 | K11: 5.8605931 | L11: 5.1862622 | M11: 4.582437 | N11: 4.7685253 | O11: 4.5161534 | P11: 2.9604799 | Q11: 1.8767377 | R11: 1.2653736 | S11: 0.9032766 | T11: 0.60028046
A12: Tangible Book Value Per Share | B12: 4.9324681 | C12: 3.711601 | D12: 3.9472236 | E12: 3.1248221 | F12: 3.7775566 | G12: 3.7654767 | H12: 4.8988335 | I12: 5.4055928 | J12: 6.0392062 | K12: 5.4666851 | L12: 4.7947995 | M12: 4.2226515 | N12: 4.5463654 | O12: 4.3114155 | P12: 2.789223 | Q12: 1.8342086 | R12: 1.2472568 | S12: 0.88334513 | T12: 0.58635983
A13: Shareholders Equity Per Share | B13: 4.9324681 | C13: 3.711601 | D13: 3.9472236 | E13: 3.1248221 | F13: 3.7775566 | G13: 3.7654767 | H13: 4.8988335 | I13: 5.4055928 | J13: 6.4232692 | K13: 5.8605931 | L13: 5.1862622 | M13: 4.582437 | N13: 4.7685253 | O13: 4.5161534 | P13: 2.9604799 | Q13: 1.8767377 | R13: 1.2653736 | S13: 0.9032766 | T13: 0.60028046
A14: Interest Debt Per Share | B14: 7.5176105 | C14: 7.7594293 | D14: 8.1212604 | E14: 8.3504754 | F14: 8.3327186 | G14: 7.2124332 | H14: 6.0430388 | I14: 5.9391546 | J14: 5.6544722 | K14: 4.0436351 | L14: 2.8270572 | M14: 1.4657209 | N14: 0.6598411 | O14: 0 | P14: 0 | Q14: 0 | R14: 0 | S14: 0 | T14: 0
A15: Market Cap | B15: 3818743810000 | C15: 3495160329570 | D15: 2695569789510 | E15: 2439367314090 | F15: 2453750882240 | G15: 1948295921320 | H15: 1010566792560 | I15: 1118725911520 | J15: 804081337040 | K15: 616670830400 | L15: 660032457120 | M15: 613182234720 | N15: 4.4667578e+11 | O15: 6.2374859e+11 | P15: 3.7369637e+11 | Q15: 2.6585391e+11 | R15: 1.6277912e+11 | S15: 113055358080 | T15: 1.3266359e+11
A16: Enterprise Value | B16: 3895186810000 | C16: 3584276329570 | D16: 2789534789510 | E16: 2548201314090 | F16: 2555332882240 | G16: 2032557921320 | H16: 1069769792560 | I16: 1207295911520 | J16: 899472337040 | K16: 683218830400 | L16: 703240457120 | M16: 634633234720 | N16: 4.4937678e+11 | O16: 6.1300259e+11 | P16: 3.6388137e+11 | Q16: 2.5459291e+11 | R16: 1.5751612e+11 | S16: 101180358080 | T16: 1.2331159e+11
... A61: Capex Per Share | B61: 0.85058702 | C61: 0.6156891 | D61: 0.69606448 | E61: 0.66033698 | F61: 0.6637219 | G61: 0.42121657 | H61: 0.56817763 | I61: 0.67164416 | J61: 0.6131113 | K61: 0.6191028 | L61: 0.49918127 | M61: 0.40312562 | N61: 0.35029936 | O61: 0.35919867 | P61: 0.2879527 | Q61: 0.083291009 | R61: 0.04851132 | S61: 0.048572842 | T61: 0.040729186

Sheet AAPL - Financial Growth FY
A1: Financial Growth
A2: Company | B2: AAPL (NASDAQ)
A3: Currency | B3: ='AAPL - Income Statement FY'!B3 -> USD
A4: Period | B4: FY
A5: Date | B5: 45927 | C5: 45563 | D5: 45199 | E5: 44828 | F5: 44464 | G5: 44100 | H5: 43736 | I5: 43372 | J5: 43008 | K5: 42637 | L5: 42273 | M5: 41909 | N5: 41545 | O5: 41181 | P5: 40810 | Q5: 40446 | R5: 40082 | S5: 39718 | T5: 39354
A7: Revenue Growth | B7: 0.064255118 | C7: 0.020219941 | D7: -0.028004605 | E7: 0.077937876 | F7: 0.33259385 | G7: 0.055120804 | H7: -0.020410776 | I7: 0.15861958 | J7: 0.063045182 | K7: -0.077342062 | L7: 0.27856342 | M7: 0.069539524 | N7: 0.092020855 | O7: 0.44581474 | P7: 0.65962438 | Q7: 0.53099547 | R7: 0.3117091 | S7: 0.35295343 | T7: 0.24286824
A8: Gross Profit Growth | B8: 0.080350669 | C8: 0.068194717 | D8: -0.009567753 | E8: 0.11741998 | F8: 0.45619117 | G8: 0.066712741 | H8: -0.033847544 | I8: 0.15482049 | J8: 0.046556614 | K8: -0.10000427 | L8: 0.32733175 | M8: 0.096930207 | N8: -0.063470333 | O8: 0.56698161 | P8: 0.70604267 | Q8: 0.5240921 | R8: 0.51206819 | S8: 0.36681383 | T8: 0.45659164
A9: Ebitgrowth | B9: 0.074859295 | C9: 0.049426782 | D9: -0.03576872 | E9: 0.091031005 | F9: 0.59870791 | G9: 0.0093921775 | H9: -0.089699644 | I9: 0.14652472 | J9: 0.05704463 | K9: -0.14225644 | L9: 0.35979357 | M9: 0.071106162 | N9: -0.098129584 | O9: 0.63025873 | P9: 0.86048409 | Q9: 0.61697449 | R9: 0.64902103 | S9: 0.56455639 | T9: 0.79657562
A10: Operating Income Growth | B10: 0.079811063 | C10: 0.077995818 | D10: -0.04300175 | E10: 0.096265225 | F10: 0.64357048 | G10: 0.036884092 | H10: -0.098282039 | I10: 0.15574465 | J10: 0.021991204 | K10: -0.15732135 | L10: 0.35668438 | M10: 0.071511664 | N10: -0.11299578 | O10: 0.63483279 | P10: 0.83791134 | Q10: 0.61697449 | R10: 0.81195219 | S10: 0.42322522 | T10: 0.79739095
A11: Net Income Growth | B11: 0.19495178 | C11: -0.03359967 | D11: -0.028135427 | E11: 0.054108576 | F11: 0.64916131 | G11: 0.03900029 | H11: -0.071811325 | I11: 0.23122583 | J11: 0.058309804 | K11: -0.14434206 | L11: 0.35140471 | M11: 0.066771067 | N11: -0.11252486 | O11: 0.60994522 | P11: 0.84985371 | Q11: 0.70163934 | R11: 0.70355813 | S11: 0.38311874 | T11: 0.7571644
A12: Epsgrowth | B12: 0.22585925 | C12: -0.0081168831 | D12: 0.0016260163 | E12: 0.084656085 | F12: 0.71299094 | G12: 0.10702341 | H12: -0.0033333333 | I12: 0.29310345 | J12: 0.11004785 | K12: -0.099137931 | L12: 0.43209877 | M12: 0.13286713 | N12: -0.10062893 | O12: 0.59 | P12: 0.81818182 | Q12: 0.66666667 | R12: 0.65 | S12: 0.42857143 | T12: 0.66270784
A13: Epsdiluted Growth | B13: 0.22697368 | C13: -0.0081566069 | D13: 0.0032733224 | E13: 0.08912656 | F13: 0.71036585 | G13: 0.1043771 | H13: -0.0033557047 | I13: 0.29565217 | J13: 0.10576923 | K13: -0.095652174 | L13: 0.42857143 | M13: 0.13380282 | N13: -0.10126582 | O13: 0.5959596 | P13: 0.83333333 | Q13: 0.6875 | R13: 0.68421053 | S13: 0.35714286 | T13: 0.73053152
A14: Weighted Average Shares Growth | B14: -0.025761769 | C14: -0.025434586 | D14: -0.029090594 | E14: -0.029058206 | F14: -0.037508214 | G14: -0.060592098 | H14: -0.068116513 | I14: -0.050192228 | J14: -0.046351004 | K14: -0.049118776 | L14: -0.054580079 | M14: -0.060479516 | N14: -0.010149489 | O14: 0.011425381 | P14: 0.016270076 | Q14: 0.018415124 | R14: 0.012959388 | S14: 0.019657896 | T14: 0.024332291
A15: Weighted Average Shares Diluted Growth | B15: -0.026180913 | C15: -0.025577916 | D15: -0.03143928 | E15: -0.031965763 | F15: -0.037841562 | G15: -0.057402558 | H15: -0.070237669 | I15: -0.047905132 | J15: -0.045195691 | K15: -0.050541086 | L15: -0.053831805 | M15: -0.061176539 | N15: -0.014484208 | O15: 0.0092988424 | P15: 0.012903546 | Q15: 0.019522494 | R15: 0.0053948527 | S15: 0.014446324 | T15: 0.01340815
A16: Dividendsper Share Growth | B16: 0.039042754 | C16: 0.04037157 | D16: 0.042731773 | E16: 0.056553488 | F16: 0.067451007 | G16: 0.061635301 | H16: 0.10494718 | I16: 0.13059796 | J16: 0.10202654 | K16: 0.10523494 | L16: 0.099085799 | M16: 0.1209969 | N16: 3.2895171 | O16: 0 | P16: 0 | Q16: 0 | R16: 0 | S16: 0 | T16: 0
A17: Operating Cash Flow Growth | B17: -0.057266562 | C17: 0.069755661 | D17: -0.095029922 | E17: 0.17409985 | F17: 0.28961004 | G17: 0.16260034 | H17: -0.1038691 | I17: 0.20566757 | J17: -0.030287932 | K17: -0.18500972 | L17: 0.36094318 | M17: 0.11267842 | N17: 0.055254051 | O17: 0.35511205 | P17: 1.0182307 | Q17: 0.83039669 | R17: 0.058670279 | S17: 0.75429616 | T17: 1.463964
... A40: Sgaexpenses Growth | B40: 0.057631145 | C40: 0.046727098 | D40: -0.0064557265 | E40: 0.14203796 | F40: 0.10328379 | G40: 0.091586736 | H40: 0.092187968 | I40: 0.094620274 | J40: 0.075172608 | K40: -0.009421453 | L40: 0.19478029 | M40: 0.10738689 | N40: 0.078685259 | O40: 0.32122648 | P40: 0.37737901 | Q40: 0.329718 | R40: 0.10316405 | S40: 0.26932163 | T40: 0.21783806
